{"objects": {"places": {"type": "GeometryCollection", "bbox": [-73.375745, 41.244010274187396, -69.941188, 42.886589], "geometries": [{"type": "Polygon", "id": "16000US2501640", "arcs": [[0, 1, 2, 3, 4, 5]]}, {"type": "Polygon", "id": "16000US2562675", "arcs": [[6, 7]]}, {"type": "Polygon", "id": "16000US2534620", "arcs": [[8]]}, {"type": "Polygon", "id": "16000US2573020", "arcs": [[9, 10]]}, {"type": "Polygon", "id": "16000US2558370", "arcs": [[11]]}, {"type": "Polygon", "id": "16000US2560627", "arcs": [[12]]}, {"type": "Polygon", "id": "16000US2518595", "arcs": [[13]]}, {"type": "Polygon", "id": "16000US2529055", "arcs": [[14, 15, 16]]}, {"type": "Polygon", "id": "16000US2551160", "arcs": [[17]]}, {"type": "Polygon", "id": "16000US2547100", "arcs": [[18]]}, {"type": "Polygon", "id": "16000US2581035", "arcs": [[19, 20, 21, 22, 23, 24]]}, {"type": "Polygon", "id": "16000US2552490", "arcs": [[25, 26, 27, 28, 29]]}, {"type": "Polygon", "id": "16000US2501260", "arcs": [[30, 31]]}, {"type": "Polygon", "id": "16000US2510015", "arcs": [[32, 33]]}, {"type": "Polygon", "id": "16000US2539152", "arcs": [[34, 35]]}, {"type": "Polygon", "id": "16000US2560505", "arcs": [[36, 37]]}, {"type": "Polygon", "id": "16000US2543615", "arcs": [[38, 39]]}, {"type": "Polygon", "id": "16000US2548710", "arcs": [[40]]}, {"type": "Polygon", "id": "16000US2534935", "arcs": [[41]]}, {"type": "Polygon", "id": "16000US2563620", "arcs": [[42]]}, {"type": "Polygon", "id": "16000US2561555", "arcs": [[43, 44]]}, {"type": "Polygon", "id": "16000US2524855", "arcs": [[45]]}, {"type": "Polygon", "id": "16000US2558615", "arcs": [[46]]}, {"type": "Polygon", "id": "16000US2531750", "arcs": [[47]]}, {"type": "Polygon", "id": "16000US2553085", "arcs": [[48]]}, {"type": "Polygon", "id": "16000US2514430", "arcs": [[49, 50]]}, {"type": "Polygon", "id": "16000US2566070", "arcs": [[51]]}, {"type": "Polygon", "id": "16000US2501360", "arcs": [[52, 53, -7, 54]]}, {"type": "Polygon", "id": "16000US2541960", "arcs": [[-37, 55]]}, {"type": "Polygon", "id": "16000US2500530", "arcs": [[56, 57]]}, {"type": "Polygon", "id": "16000US2556095", "arcs": [[58]]}, {"type": "Polygon", "id": "16000US2516810", "arcs": [[59, 60, 61, 62]]}, {"type": "Polygon", "id": "16000US2575820", "arcs": [[63, -63, 64, 65]]}, {"type": "Polygon", "id": "16000US2524960", "arcs": [[66, 67, 68, 69]]}, {"type": "Polygon", "id": "16000US2528460", "arcs": [[70]]}, {"type": "Polygon", "id": "16000US2517860", "arcs": [[71, 72]]}, {"type": "Polygon", "id": "16000US2536335", "arcs": [[73, 74, 75]]}, {"type": "Polygon", "id": "16000US2539660", "arcs": [[76]]}, {"type": "Polygon", "id": "16000US2520310", "arcs": [[77, 78]]}, {"type": "Polygon", "id": "16000US2530420", "arcs": [[79, 80, 81, 82, 83, 84]]}, {"type": "Polygon", "id": "16000US2555090", "arcs": [[85, 86, 87, 88]]}, {"type": "Polygon", "id": "16000US2518875", "arcs": [[89]]}, {"type": "Polygon", "id": "16000US2569205", "arcs": [[90, 91, 92, 93]]}, {"type": "MultiPolygon", "id": "16000US2548780", "arcs": [[[94, 95]], [[96, 97, 98, 99]]]}, {"type": "Polygon", "id": "16000US2556165", "arcs": [[100, 101, 102, -22, 103, 104]]}, {"type": "MultiPolygon", "id": "16000US2507000", "arcs": [[[105]], [[106]], [[107, 108]], [[109]], [[110]], [[111, 112]], [[113, 114, 115, 116, 117, 118, 119, 120, 121, 122, 123, 124, 125, 126, 127, 128]]]}, {"type": "MultiPolygon", "id": "16000US2538435", "arcs": [[[129]], [[130, 131, 132]]]}, {"type": "Polygon", "id": "16000US2541410", "arcs": [[133]]}, {"type": "Polygon", "id": "16000US2519370", "arcs": [[134, 135, 136, 137]]}, {"type": "Polygon", "id": "16000US2575050", "arcs": [[138]]}, {"type": "Polygon", "id": "16000US2545560", "arcs": [[139, 140, -115, 141, -129, 142, 143, 144]]}, {"type": "Polygon", "id": "16000US2529405", "arcs": [[145, 146]]}, {"type": "Polygon", "id": "16000US2553960", "arcs": [[147]]}, {"type": "Polygon", "id": "16000US2535075", "arcs": [[148, 149]]}, {"type": "MultiPolygon", "id": "16000US2559105", "arcs": [[[150]], [[151]], [[152]], [[-28, 153, 154, 155, -133, 156, 157]]]}, {"type": "Polygon", "id": "16000US2509000", "arcs": [[-83, 158, 159]]}, {"type": "Polygon", "id": "16000US2567000", "arcs": [[160, 161, -74, 162, 163]]}, {"type": "Polygon", "id": "16000US2545245", "arcs": [[-31, 164, 165, 166]]}, {"type": "Polygon", "id": "16000US2525485", "arcs": [[167, 168]]}, {"type": "Polygon", "id": "16000US2507740", "arcs": [[169, 170, -80, 171]]}, {"type": "Polygon", "id": "16000US2502690", "arcs": [[172, 173]]}, {"type": "Polygon", "id": "16000US2505595", "arcs": [[174, -155, 175]]}, {"type": "Polygon", "id": "16000US2551230", "arcs": [[176]]}, {"type": "Polygon", "id": "16000US2542670", "arcs": [[177, 178, 179, 180]]}, {"type": "MultiPolygon", "id": "16000US2531680", "arcs": [[[181]], [[182]], [[183]], [[184]], [[185]]]}, {"type": "Polygon", "id": "16000US2557845", "arcs": [[186, 187]]}, {"type": "Polygon", "id": "16000US2552770", "arcs": [[-79, 188]]}, {"type": "Polygon", "id": "16000US2558965", "arcs": [[189, 190]]}, {"type": "Polygon", "id": "16000US2554450", "arcs": [[-179, 191]]}, {"type": "Polygon", "id": "16000US2580370", "arcs": [[192]]}, {"type": "Polygon", "id": "16000US2559210", "arcs": [[-166, 193]]}, {"type": "Polygon", "id": "16000US2567700", "arcs": [[-103, 194, 195, 196, 197, 198, -23]]}, {"type": "Polygon", "id": "16000US2529090", "arcs": [[-16, 199, 200, 201]]}, {"type": "Polygon", "id": "16000US2541532", "arcs": [[202]]}, {"type": "Polygon", "id": "16000US2546295", "arcs": [[-53, 203]]}, {"type": "Polygon", "id": "16000US2519400", "arcs": [[204, -200, -15, 205]]}, {"type": "Polygon", "id": "16000US2521815", "arcs": [[206]]}, {"type": "Polygon", "id": "16000US2520380", "arcs": [[207, 208, 209, 210]]}, {"type": "Polygon", "id": "16000US2538230", "arcs": [[211]]}, {"type": "Polygon", "id": "16000US2579950", "arcs": [[212, 213]]}, {"type": "Polygon", "id": "16000US2570815", "arcs": [[214, 215]]}, {"type": "Polygon", "id": "16000US2582595", "arcs": [[216, 217, 218, 219, 220]]}, {"type": "Polygon", "id": "16000US2575505", "arcs": [[221, 222]]}, {"type": "Polygon", "id": "16000US2569585", "arcs": [[223]]}, {"type": "Polygon", "id": "16000US2503705", "arcs": [[224]]}, {"type": "Polygon", "id": "16000US2547730", "arcs": [[225, 226]]}, {"type": "Polygon", "id": "16000US2568680", "arcs": [[-157, -132, 227, 228]]}, {"type": "Polygon", "id": "16000US2560295", "arcs": [[229, 230, 231, 232]]}, {"type": "Polygon", "id": "16000US2546225", "arcs": [[-213, 233]]}, {"type": "Polygon", "id": "16000US2530840", "arcs": [[-137, 234, 235, 236, 237, 238]]}, {"type": "Polygon", "id": "16000US2538715", "arcs": [[239, 240, -67, 241]]}, {"type": "Polygon", "id": "16000US2540115", "arcs": [[-196, 242, 243, 244]]}, {"type": "Polygon", "id": "16000US2562535", "arcs": [[245, 246, -118, 247, -3]]}, {"type": "Polygon", "id": "16000US2572600", "arcs": [[248, 249, 250, -140, 251]]}, {"type": "Polygon", "id": "16000US2521990", "arcs": [[252, 253, 254, -119, -247, 255]]}, {"type": "Polygon", "id": "16000US2537000", "arcs": [[256]]}, {"type": "Polygon", "id": "16000US2573440", "arcs": [[-251, 257, 258, -116, -141]]}, {"type": "Polygon", "id": "16000US2526150", "arcs": [[-188, 259]]}, {"type": "Polygon", "id": "16000US2537490", "arcs": [[260, -29, -158, -229, 261, -40, 262, 263, 264]]}, {"type": "Polygon", "id": "16000US2503690", "arcs": [[-209, 265, -221, 266, 267, 268, 269, -87, 270, -35, 271]]}, {"type": "Polygon", "id": "16000US2513205", "arcs": [[272, -120, -255]]}, {"type": "Polygon", "id": "16000US2555745", "arcs": [[-124, 273, -112, 274, 275, -170, 276, 277]]}, {"type": "Polygon", "id": "16000US2577890", "arcs": [[-237, 278, -164, 279, 280]]}, {"type": "Polygon", "id": "16000US2546330", "arcs": [[-135, 281]]}, {"type": "Polygon", "id": "16000US2523000", "arcs": [[282, 283, 284, 285]]}, {"type": "Polygon", "id": "16000US2569170", "arcs": [[286, 287]]}, {"type": "Polygon", "id": "16000US2578972", "arcs": [[-171, -276, 288, 289, 290, -81]]}, {"type": "Polygon", "id": "16000US2527100", "arcs": [[-216, 291]]}, {"type": "Polygon", "id": "16000US2507140", "arcs": [[-34, 292, -181, 293]]}, {"type": "Polygon", "id": "16000US2507945", "arcs": [[294]]}, {"type": "Polygon", "id": "16000US2512960", "arcs": [[295, -222]]}, {"type": "Polygon", "id": "16000US2518980", "arcs": [[296, -92]]}, {"type": "Polygon", "id": "16000US2524190", "arcs": [[297]]}, {"type": "Polygon", "id": "16000US2551405", "arcs": [[298]]}, {"type": "Polygon", "id": "16000US2555535", "arcs": [[299]]}, {"type": "Polygon", "id": "16000US2559700", "arcs": [[300, -211, 301, -190]]}, {"type": "Polygon", "id": "16000US2563655", "arcs": [[302, 303, 304, 305, -60, -64, 306, 307, -219]]}, {"type": "Polygon", "id": "16000US2566035", "arcs": [[308, -307, -66, 309, 310]]}, {"type": "Polygon", "id": "16000US2516285", "arcs": [[-176, -154, -27, 311]]}, {"type": "Polygon", "id": "16000US2532275", "arcs": [[312]]}, {"type": "Polygon", "id": "16000US2560050", "arcs": [[313, -265, 314, 315, -244, 316]]}, {"type": "Polygon", "id": "16000US2500135", "arcs": [[-291, 317, 318, -159, -82]]}, {"type": "Polygon", "id": "16000US2533185", "arcs": [[-97, 319]]}, {"type": "Polygon", "id": "16000US2538575", "arcs": [[320]]}, {"type": "Polygon", "id": "16000US2548220", "arcs": [[-287, 321, 322, 323]]}, {"type": "Polygon", "id": "16000US2549165", "arcs": [[-233, 324]]}, {"type": "Polygon", "id": "16000US2550862", "arcs": [[325, 326, 327, 328]]}, {"type": "MultiPolygon", "id": "16000US2554275", "arcs": [[[329, -95]], [[330, -99]]]}, {"type": "Polygon", "id": "16000US2516840", "arcs": [[-44, 331, 332, 333]]}, {"type": "Polygon", "id": "16000US2527445", "arcs": [[334]]}, {"type": "Polygon", "id": "16000US2531575", "arcs": [[-240, 335]]}, {"type": "Polygon", "id": "16000US2535250", "arcs": [[336, 337, -25, 338, -6, 339, -249, 340, 341]]}, {"type": "Polygon", "id": "16000US2570325", "arcs": [[342]]}, {"type": "Polygon", "id": "16000US2580545", "arcs": [[-24, -199, 343, -1, -339]]}, {"type": "Polygon", "id": "16000US2504965", "arcs": [[344]]}, {"type": "Polygon", "id": "16000US2516530", "arcs": [[-127, 345, 346]]}, {"type": "Polygon", "id": "16000US2517370", "arcs": [[347, 348]]}, {"type": "Polygon", "id": "16000US2539730", "arcs": [[349]]}, {"type": "Polygon", "id": "16000US2572460", "arcs": [[350]]}, {"type": "Polygon", "id": "16000US2530630", "arcs": [[351]]}, {"type": "Polygon", "id": "16000US2579705", "arcs": [[352]]}, {"type": "Polygon", "id": "16000US2503040", "arcs": [[353, -333]]}, {"type": "Polygon", "id": "16000US2509875", "arcs": [[354, 355, 356, -20, -338, 357]]}, {"type": "Polygon", "id": "16000US2563840", "arcs": [[-290, 358, -318]]}, {"type": "Polygon", "id": "16000US2537735", "arcs": [[359]]}, {"type": "Polygon", "id": "16000US2543755", "arcs": [[360]]}, {"type": "Polygon", "id": "16000US2579495", "arcs": [[361]]}, {"type": "Polygon", "id": "16000US2549700", "arcs": [[362, -206, -17, -202, 363, -61, -306]]}, {"type": "Polygon", "id": "16000US2505105", "arcs": [[-5, 364, -258, -250, -340]]}, {"type": "Polygon", "id": "16000US2553680", "arcs": [[-355, 365]]}, {"type": "Polygon", "id": "16000US2513310", "arcs": [[366]]}, {"type": "Polygon", "id": "16000US2516635", "arcs": [[367]]}, {"type": "Polygon", "id": "16000US2506050", "arcs": [[368]]}, {"type": "Polygon", "id": "16000US2509070", "arcs": [[369]]}, {"type": "Polygon", "id": "16000US2502515", "arcs": [[370]]}, {"type": "Polygon", "id": "16000US2515340", "arcs": [[371]]}, {"type": "Polygon", "id": "16000US2530980", "arcs": [[372, 373]]}, {"type": "Polygon", "id": "16000US2537385", "arcs": [[374]]}, {"type": "Polygon", "id": "16000US2541200", "arcs": [[-373, 375]]}, {"type": "Polygon", "id": "16000US2568120", "arcs": [[376, 377]]}, {"type": "Polygon", "id": "16000US2573055", "arcs": [[378]]}, {"type": "Polygon", "id": "16000US2529230", "arcs": [[379]]}, {"type": "Polygon", "id": "16000US2572845", "arcs": [[380, 381]]}, {"type": "Polygon", "id": "16000US2538820", "arcs": [[-328, 382]]}, {"type": "Polygon", "id": "16000US2550005", "arcs": [[383]]}, {"type": "Polygon", "id": "16000US2550880", "arcs": [[384]]}, {"type": "Polygon", "id": "16000US2562300", "arcs": [[385, 386]]}, {"type": "Polygon", "id": "16000US2504790", "arcs": [[387]]}, {"type": "Polygon", "id": "16000US2562465", "arcs": [[-286, 388]]}, {"type": "Polygon", "id": "16000US2558790", "arcs": [[389]]}, {"type": "Polygon", "id": "16000US2547590", "arcs": [[390]]}, {"type": "Polygon", "id": "16000US2575960", "arcs": [[-226, 391]]}, {"type": "Polygon", "id": "16000US2575680", "arcs": [[392]]}, {"type": "Polygon", "id": "16000US2570115", "arcs": [[393]]}, {"type": "Polygon", "id": "16000US2542180", "arcs": [[394]]}, {"type": "Polygon", "id": "16000US2536020", "arcs": [[395]]}, {"type": "Polygon", "id": "16000US2576030", "arcs": [[-238, -281, 396, 397]]}, {"type": "Polygon", "id": "16000US2525172", "arcs": [[398]]}, {"type": "Polygon", "id": "16000US2547800", "arcs": [[399]]}, {"type": "Polygon", "id": "16000US2578850", "arcs": [[-10, 400]]}, {"type": "Polygon", "id": "16000US2526500", "arcs": [[401]]}, {"type": "Polygon", "id": "16000US2551790", "arcs": [[402]]}, {"type": "Polygon", "id": "16000US2523840", "arcs": [[403]]}, {"type": "Polygon", "id": "16000US2562780", "arcs": [[404, -168]]}, {"type": "Polygon", "id": "16000US2555990", "arcs": [[-277, -172, -85, 405, 406]]}, {"type": "Polygon", "id": "16000US2560820", "arcs": [[407]]}, {"type": "Polygon", "id": "16000US2508050", "arcs": [[408]]}, {"type": "Polygon", "id": "16000US2509210", "arcs": [[-114, -142]]}, {"type": "Polygon", "id": "16000US2550285", "arcs": [[409]]}, {"type": "Polygon", "id": "16000US2578795", "arcs": [[410, -311, 411, -268]]}, {"type": "Polygon", "id": "16000US2575365", "arcs": [[412]]}, {"type": "Polygon", "id": "16000US2540885", "arcs": [[-323, 413]]}, {"type": "Polygon", "id": "16000US2578410", "arcs": [[414]]}, {"type": "Polygon", "id": "16000US2561205", "arcs": [[415]]}, {"type": "Polygon", "id": "16000US2531050", "arcs": [[416]]}, {"type": "Polygon", "id": "16000US2526780", "arcs": [[417]]}, {"type": "Polygon", "id": "16000US2514570", "arcs": [[-69, 418]]}, {"type": "Polygon", "id": "16000US2518840", "arcs": [[419, -304, 420]]}, {"type": "Polygon", "id": "16000US2511000", "arcs": [[-4, -248, -117, -259, -365]]}, {"type": "Polygon", "id": "16000US2539835", "arcs": [[-344, -198, 421, -256, -246, -2]]}, {"type": "Polygon", "id": "16000US2537875", "arcs": [[-197, -245, -316, 422, -253, -422]]}, {"type": "Polygon", "id": "16000US2513660", "arcs": [[423, -161, -279, -236]]}, {"type": "Polygon", "id": "16000US2581245", "arcs": [[424]]}, {"type": "Polygon", "id": "16000US2564460", "arcs": [[-50, 425]]}, {"type": "Polygon", "id": "16000US2537595", "arcs": [[426, -30, -261, -314, 427, -101]]}, {"type": "Polygon", "id": "16000US2500840", "arcs": [[-397, -280, -163, -76, 428]]}, {"type": "Polygon", "id": "16000US2561940", "arcs": [[429]]}, {"type": "Polygon", "id": "16000US2571445", "arcs": [[430]]}, {"type": "Polygon", "id": "16000US2556585", "arcs": [[-423, -315, -264, 431, 432, -121, -273, -254]]}, {"type": "Polygon", "id": "16000US2582000", "arcs": [[433]]}, {"type": "Polygon", "id": "16000US2507385", "arcs": [[434]]}, {"type": "Polygon", "id": "16000US2513450", "arcs": [[435]]}, {"type": "Polygon", "id": "16000US2573930", "arcs": [[436]]}, {"type": "Polygon", "id": "16000US2534550", "arcs": [[437, 438]]}, {"type": "Polygon", "id": "16000US2516740", "arcs": [[-421, -303, -218, 439]]}, {"type": "Polygon", "id": "16000US2555070", "arcs": [[-88, -270, 440, 441]]}, {"type": "Polygon", "id": "16000US2501430", "arcs": [[442]]}, {"type": "Polygon", "id": "16000US2549710", "arcs": [[443, -284]]}, {"type": "Polygon", "id": "16000US2523070", "arcs": [[-94, 444]]}, {"type": "Polygon", "id": "16000US2538960", "arcs": [[-231, 445]]}, {"type": "Polygon", "id": "16000US2531295", "arcs": [[446]]}, {"type": "Polygon", "id": "16000US2539485", "arcs": [[447]]}, {"type": "Polygon", "id": "16000US2544140", "arcs": [[448, 449, 450, 451, -143, -128, -347, 452, -348]]}, {"type": "Polygon", "id": "16000US2541725", "arcs": [[-125, -278, -407, 453]]}, {"type": "Polygon", "id": "16000US2523875", "arcs": [[-149, 454]]}, {"type": "Polygon", "id": "16000US2545000", "arcs": [[-57, 455, 456, 457, -386, 458]]}, {"type": "Polygon", "id": "16000US2528425", "arcs": [[-342, 459]]}, {"type": "Polygon", "id": "16000US2572250", "arcs": [[-428, -317, -243, -195, -102]]}, {"type": "Polygon", "id": "16000US2563690", "arcs": [[-72, 460]]}, {"type": "Polygon", "id": "16000US2552144", "arcs": [[-381, 461]]}, {"type": "Polygon", "id": "16000US2563345", "arcs": [[-377, 462]]}, {"type": "Polygon", "id": "16000US2545500", "arcs": [[-89, -442, 463]]}, {"type": "Polygon", "id": "16000US2579390", "arcs": [[464]]}, {"type": "Polygon", "id": "16000US2506170", "arcs": [[-457, 465]]}, {"type": "Polygon", "id": "16000US2580195", "arcs": [[-104, -21, -357, 466]]}, {"type": "MultiPolygon", "id": "16000US2574210", "arcs": [[[-450, 467]], [[-144, -452, 468]]]}, {"type": "Polygon", "id": "16000US2521115", "arcs": [[469]]}, {"type": "Polygon", "id": "16000US2500590", "arcs": [[470]]}, {"type": "Polygon", "id": "16000US2527147", "arcs": [[-326, 471]]}, {"type": "Polygon", "id": "16000US2530175", "arcs": [[472]]}, {"type": "Polygon", "id": "16000US2581005", "arcs": [[-433, 473, -109, 474, -122]]}, {"type": "Polygon", "id": "16000US2549200", "arcs": [[-173, 475]]}, {"type": "Polygon", "id": "16000US2503355", "arcs": [[476]]}, {"type": "Polygon", "id": "16000US2546785", "arcs": [[477]]}, {"type": "Polygon", "id": "16000US2540710", "arcs": [[-146, 478, -439, 479]]}, {"type": "Polygon", "id": "16000US2571970", "arcs": [[480]]}]}}, "type": "Topology", "transform": {"translate": [-73.375745, 41.244010274187396], "scale": [0.0003434900490049003, 0.00016427430001126164]}, "arcs": [[[6385, 7257], [94, -3]], [[6479, 7254], [11, -73], [23, -49], [17, -3]], [[6530, 7129], [0, -38], [-6, -29]], [[6524, 7062], [-5, -19], [-22, -23], [-25, 22]], [[6472, 7042], [-64, 51], [-27, 12], [-32, 22], [1, -10], [-24, 9]], [[6326, 7126], [59, 131]], [[2442, 6733], [8, 6], [31, 7], [16, 27], [39, -1], [0, 5]], [[2536, 6777], [3, -9], [42, -73], [-8, -12], [-37, 1], [-3, -120], [-19, 34], [-12, -24], [-19, -12], [-4, -17], [-27, 6], [-21, -4], [11, 186]], [[322, 6517], [30, -25], [22, 12], [-6, 25], [10, 5], [11, 27], [6, 0], [-1, -120], [3, -24], [-53, -12], [0, 33], [-10, 0], [-13, 53], [1, 26]], [[7722, 3061], [-31, 39]], [[7691, 3100], [10, 25], [-4, 44], [-7, 21], [21, -12], [12, 7], [45, -92], [0, -59], [-29, -50], [-17, -2], [-14, 32], [9, 4], [8, 29], [-3, 14]], [[7223, 9020], [14, 5], [22, -7], [3, -12], [28, 16], [15, 22], [22, -30], [1, -45], [-7, -11], [9, -12], [-17, -7], [-3, -21], [-32, 23], [-16, -40], [-2, 10], [-20, 15], [5, 31], [-18, 30], [-4, 33]], [[8322, 1916], [8, 28], [-3, 32], [12, 10], [8, -14], [-25, -56]], [[3786, 5943], [4, 1], [3, 70], [8, -4], [72, -9], [19, 89], [24, 4], [12, -148], [-23, 31], [-13, 6], [-24, -16], [-21, -1], [-6, 9], [-54, -46], [-11, -22], [10, 36]], [[9603, 2811], [16, 24], [13, -7], [3, -25], [29, -8], [-4, -34], [11, 5], [-5, -32], [-20, -12], [-7, -20], [37, -42]], [[9676, 2660], [-19, -33], [-6, 15], [-26, 0], [1, 22], [-10, 23], [-12, -1], [-6, -46], [-12, -11], [-3, 24]], [[9583, 2653], [-2, 40], [8, -2], [5, 30], [-15, 15], [7, 41], [22, 16], [-5, 18]], [[7834, 3074], [14, 0], [10, 48], [67, -7], [-20, -30], [14, -22], [5, -36], [-31, -28], [-23, 42], [-22, 20], [-19, 7], [5, 6]], [[3722, 6272], [21, 17], [6, 51], [19, -39], [28, 20], [3, -51], [-11, -19], [-20, -14], [16, -10], [5, -38], [-21, 3], [-25, -6], [-14, 3], [-2, 52], [-5, 31]], [[6321, 7438], [46, 84], [20, 24], [37, 21], [0, 96], [-4, 78]], [[6420, 7741], [101, 86]], [[6521, 7827], [46, -180]], [[6567, 7647], [-5, -10], [14, -24], [13, -127]], [[6589, 7486], [-34, -2], [-83, -59], [-11, -43], [-24, 18], [-73, -61]], [[6364, 7339], [-51, 85], [8, 14]], [[6815, 8044], [15, -3], [2, 30], [23, -2], [17, -11], [20, -23], [11, 6], [6, -11]], [[6909, 8030], [66, -44], [100, -51], [14, -10], [12, 7], [24, -8], [43, -27]], [[7168, 7897], [3, -82], [-9, 5], [-12, -50], [-88, -156]], [[7062, 7614], [-21, 11], [-86, 92]], [[6955, 7717], [-54, 68], [-76, 171], [-10, 88]], [[7195, 9677], [-25, 9], [-11, 36], [-21, -10], [-22, -45], [-7, -25], [-19, -34]], [[7090, 9608], [-14, -10], [-37, -6], [-33, 16], [-31, 137], [-72, 110], [111, 36], [50, 43], [51, 49], [12, 8], [38, 8], [43, -242], [-13, -80]], [[7986, 3005], [19, 45], [12, 6], [1, 17], [-10, 13], [-2, 25], [-20, 46], [84, 70], [-3, -35], [16, -5], [-3, -56], [6, -36], [15, 2], [10, -31]], [[8111, 3066], [-62, -28], [-33, -33], [-20, -9], [-10, 9]], [[8515, 2268], [-6, -4], [-24, -58], [-11, -60]], [[8474, 2146], [-19, 6], [-9, 51], [1, 19], [-15, 42], [-1, 28], [53, 5], [31, -29]], [[8370, 2032], [-6, -16]], [[8364, 2016], [-7, 19], [15, 78], [14, -32], [15, -16], [-17, -8], [-14, -25]], [[7105, 7381], [-4, -101], [10, -14], [12, 3], [12, -49], [34, -14], [14, -16], [2, -20], [14, -11], [-8, -23], [-15, 0], [-11, 12], [-40, -8], [-23, 7], [-2, 74], [-11, 44], [-1, 91], [-3, 17]], [[7085, 7373], [20, 8]], [[7463, 5235], [25, 47], [8, -12], [5, 16], [20, -38], [7, 3], [-2, 24], [21, 8], [2, 27], [21, -6], [-6, -13], [31, 5], [2, -25], [19, -2], [-8, -39], [20, -22], [-13, -32], [7, -52], [-8, -25], [-22, -15], [-18, 42], [-12, 17], [-33, 12], [-36, -18], [-10, -12], [-10, 12], [2, 33], [-12, 65]], [[225, 6771], [-6, 29], [5, 19], [0, 34], [27, 14], [9, -50], [12, -7], [6, 44], [9, 27], [0, -37], [7, -41], [16, -29], [4, -27], [-4, -30], [-21, 26], [-13, -8], [-18, -44], [-3, 56], [-39, -1], [9, 25]], [[2221, 7532], [10, 105], [6, -6], [7, -50], [27, 5], [21, 14], [33, -22], [5, -17], [4, 20], [13, 7], [-3, -42], [-33, -71], [-10, -33], [-69, -16], [-6, 44], [-10, -3], [5, 65]], [[5068, 7940], [-26, -16], [14, -27], [-14, 2], [-12, -38]], [[5030, 7861], [-9, -13], [-10, 38], [-8, 1], [-3, -17], [-14, -15], [-6, -38], [-31, 10], [-4, 39], [12, 23], [16, 6], [17, 33], [12, 12], [31, -8], [7, 8], [28, 0]], [[6128, 5063], [30, -10], [34, 11], [3, 26], [15, -3], [-6, 22], [12, -4], [3, -22], [7, 15], [12, -13], [-17, -33], [26, -51], [-26, -85], [-34, -33], [-24, 9], [-2, 82], [-12, 34], [-18, 17], [-3, 38]], [[1441, 5712], [20, 164], [28, -3], [19, 23], [9, -30], [-6, -28], [23, -6], [5, -17], [-10, -51], [1, -23], [-8, -13], [-48, 4], [-15, -15], [-18, -5]], [[1401, 6147], [39, 67], [10, -31], [35, -14], [-7, -44], [14, -33], [16, -26], [-19, -52], [-23, -95], [-117, 139], [52, 89]], [[3422, 7617], [26, 25], [11, 4], [13, -12], [23, -2], [0, -49], [-12, -18], [2, -42], [-19, 18], [-29, 5], [-12, 43], [-3, 28]], [[4875, 7190], [16, 29]], [[4891, 7219], [5, -27], [14, 9], [7, 29], [16, -12], [7, -38], [19, -10], [0, 10], [16, -4], [-7, -36], [-10, -5], [-37, -39], [-3, -24], [-26, -5], [-26, 30], [21, 3], [15, 16], [14, 45], [-16, 2], [-25, 27]], [[3980, 6057], [0, 29], [16, 66], [23, 26], [7, 20], [4, -47], [30, 6], [9, -27], [-11, -9], [13, -53], [-15, -51], [-14, -2], [-52, 32], [-10, 10]], [[2458, 7044], [10, -5], [3, -32], [13, 12], [34, 13], [13, -4], [4, -16]], [[2535, 7012], [3, -51], [17, -4], [-16, -140], [-3, -40]], [[2442, 6733], [4, 94], [12, 217]], [[8370, 2032], [19, -2], [7, -19], [-22, 8], [-19, -45], [-6, -29], [-14, -7], [29, 78]], [[7161, 2631], [-9, 33]], [[7152, 2664], [0, 23], [14, 66], [5, 2], [39, -28], [16, -42], [12, 3], [-21, -50], [-47, -15], [-9, 8]], [[6731, 4139], [4, 30], [-4, 28], [31, 37], [6, 22], [15, 23], [4, 57], [5, 20], [63, -80], [-10, -63], [-45, -159], [-25, 16], [-18, -3], [-10, 14], [-10, -1], [-8, 36], [2, 23]], [[9390, 2687], [2, 7], [61, 21]], [[9453, 2715], [32, -212]], [[9485, 2503], [-67, -29], [-49, 7]], [[9369, 2481], [32, 95], [19, 40], [-19, 57], [-11, 14]], [[9333, 2734], [39, -17], [5, -23], [13, -7]], [[9369, 2481], [-31, 3], [-73, -23]], [[9265, 2461], [-12, 5], [7, 35], [15, 17], [16, 30], [14, 41], [16, 5], [21, 44], [14, 14], [8, 31], [-6, 19], [-18, 8], [-7, 24]], [[5498, 6610], [10, 141]], [[5508, 6751], [135, -38], [119, -36], [6, -33], [16, 12], [21, -55]], [[5805, 6601], [12, -84]], [[5817, 6517], [-30, -79], [-42, -52], [8, -73], [7, -13], [4, -38], [16, -5], [-22, -63], [-62, -27], [-121, 134], [-107, 64], [32, 128], [3, 76], [-5, 41]], [[7305, 5036], [13, 46], [13, 8], [29, -18], [13, -19], [13, -62], [-8, -21], [13, -8], [-27, -26], [-3, -41], [3, -12], [-33, 14], [-4, 72], [-10, 25], [-13, 7], [1, 35]], [[7875, 4770], [-26, 13], [-15, -9], [-18, 43]], [[7816, 4817], [7, 46], [-12, 52], [16, 4], [32, 35], [16, 7], [3, -45], [14, 7], [13, -24], [29, -11], [-16, -31], [-24, -4], [-15, -25], [-4, -58]], [[2289, 5041], [154, -51]], [[2443, 4990], [15, -182], [-122, -24], [-26, -33], [-72, 3], [-3, 35]], [[2235, 4789], [1, 84], [8, 39], [36, 108], [9, 21]], [[5664, 7262], [-36, -182], [-78, -27], [-27, 209], [42, 81], [99, -81]], [[5271, 8693], [10, 22], [33, -1], [1, -46], [4, -15], [-19, -37], [-70, -30]], [[5230, 8586], [-2, 14], [11, 51], [-1, 27], [22, 0], [11, 15]], [[6853, 5630], [43, -4], [89, 0]], [[6985, 5626], [-14, -200]], [[6971, 5426], [-61, -50], [1, -5]], [[6911, 5371], [-58, -47]], [[6853, 5324], [-15, 31], [-1, 56], [-23, 16]], [[6814, 5427], [21, 120], [18, 83]], [[8470, 2117], [10, 10]], [[8480, 2127], [12, -29], [16, -15], [6, 6]], [[8514, 2089], [-3, -20], [-13, -33], [-7, -1]], [[8491, 2035], [-10, 39], [-12, 1], [8, 15], [-7, 27]], [[4770, 5134], [118, 47], [1, -125], [-9, -3], [19, -57], [-5, -38], [-47, 19], [-16, -6], [-8, 45], [5, 9], [-38, 2], [-1, 32], [-8, 15], [2, 15], [10, -3], [-23, 48]], [[8083, 1928], [8, 14], [5, 30], [51, 58], [12, 3]], [[8159, 2033], [-26, -116], [0, -50], [5, -39]], [[8138, 1828], [-24, 5]], [[8114, 1833], [-1, 34], [-7, 22], [-3, 35], [-14, -13], [-6, 17]], [[7929, 4463], [-3, -4]], [[7926, 4459], [3, 4]], [[7777, 4431], [32, 68]], [[7809, 4499], [7, -11], [26, -9], [11, -18], [6, -29], [12, -22]], [[7871, 4410], [-17, -5], [-12, -20], [-4, 18], [-27, -27]], [[7811, 4376], [-34, 55]], [[6710, 7986], [-13, -151]], [[6697, 7835], [-17, -34], [-7, -2], [-39, -82], [7, -29], [-14, -3], [-5, -26]], [[6622, 7659], [-55, -12]], [[6521, 7827], [12, 11], [-15, 128]], [[6518, 7966], [28, 10], [12, 25], [19, 20], [18, -3], [7, 19], [12, 3], [41, -40], [55, -14]], [[7084, 6592], [21, -3], [9, 12], [5, 39], [23, -52], [-8, -56], [-16, 11], [0, 17], [-15, 19], [-11, -5], [-8, 18]], [[7038, 6499], [20, 12], [8, -10], [-17, -21], [-11, 19]], [[7016, 6780], [8, -12], [18, -4], [10, -34], [1, -35], [-20, 16], [-29, 53]], [[7004, 6764], [12, 16]], [[6982, 6503], [21, 24], [8, 40], [30, 54], [13, -7], [-3, -17], [-16, -20], [-19, -67], [-16, -15], [-17, -4], [-1, 12]], [[6948, 6600], [18, -6], [-8, -53], [-9, 4], [0, 28], [-8, 14], [7, 13]], [[6892, 6462], [-20, 7]], [[6872, 6469], [-7, 38], [13, 15], [18, 33], [27, 2], [-3, -21], [-10, 7], [-11, -16], [-12, -35], [5, -30]], [[6436, 6450], [36, -55], [36, 46], [27, 75], [20, 49], [20, 8], [16, 73], [2, 28], [14, 20], [-2, 37], [-51, 10], [-27, -27], [-37, -58], [-31, -45]], [[6459, 6611], [-16, 23], [-15, -2], [-5, 27], [7, 12], [-22, 58], [1, 23], [18, 42]], [[6427, 6794], [18, -6], [38, 12], [15, 23]], [[6498, 6823], [10, -3], [23, 32], [-3, 17], [14, 6], [15, -28], [17, -11], [1, -70], [17, -18], [35, 1], [23, 9], [42, 27], [21, 63], [17, -1], [-9, 19], [-17, 9]], [[6704, 6875], [-8, 40], [-15, 12], [22, 59]], [[6703, 6986], [18, 13], [-11, -29], [15, -15], [31, 3]], [[6756, 6958], [20, -9], [12, -14], [14, 22], [34, -18], [21, 22], [8, 19], [5, 31], [7, 9]], [[6877, 7020], [22, -21], [13, 18], [15, -3], [6, -18], [19, -3], [5, -29]], [[6957, 6964], [-24, -22], [-1, -20], [-10, -19], [-23, -13], [-12, -64], [69, -6], [2, -37]], [[6958, 6783], [-11, -23], [-25, -11], [-26, -35], [-25, -101], [-50, -13], [-33, -35], [32, -34], [1, -21], [-13, -20], [-7, -26]], [[6801, 6464], [-6, -5], [1, -30], [18, -69], [-22, -72]], [[6792, 6288], [-18, 4], [-19, -12], [6, -21], [-24, -30], [-19, 22], [-23, -4], [-22, -11], [-17, 8], [-3, -21], [-13, 2], [-9, -24], [-17, -18], [-20, 7], [-8, -13], [11, -21], [0, -44], [-49, -54], [10, -28], [-23, -42]], [[6535, 5988], [-2, 2]], [[6533, 5990], [-33, 48], [-11, 119], [-17, 18], [-18, -21], [-47, 78], [4, 18], [-4, 30], [-26, 0], [-5, 24], [-8, 4]], [[6368, 6308], [-9, 17]], [[6359, 6325], [36, 70], [41, 55]], [[7394, 7550], [6, 12], [1, -29], [-7, 17]], [[7269, 7677], [11, -2], [31, 83], [20, 19], [34, -25], [10, 12], [-1, -66], [-27, -51], [-5, -44], [18, 5], [39, 73], [8, -14], [-8, -26], [-6, -53], [-16, -19], [-17, 24], [-30, -7], [-64, -69]], [[7266, 7517], [-55, 35]], [[7211, 7552], [13, 7], [12, 22], [-2, 24], [12, 11], [-1, 20], [24, 41]], [[2539, 8135], [16, 32], [1, 24], [8, 19], [13, -10], [8, -78], [21, 5], [17, -35], [-5, -12], [-20, 35], [-50, -78], [-4, 3], [11, 34], [1, 58], [-17, 3]], [[1859, 6331], [189, 47], [0, -10], [34, -5], [34, 14], [19, -22], [4, -24], [9, 20], [10, -13], [14, 0], [14, 17], [30, 13]], [[2216, 6368], [4, -24]], [[2220, 6344], [-63, -74], [-51, -222], [-13, -60], [-33, -14]], [[2060, 5974], [-58, -13], [6, 54], [-5, 34], [14, 38], [-55, 80], [7, 8], [2, 26], [8, 20], [-16, 17], [-21, 6], [-12, 37], [-26, 2], [-11, 11], [-33, -9], [-1, 46]], [[5062, 6212], [12, 32], [1, 26], [13, 11], [16, -9], [3, 13], [32, 9], [14, -11], [16, -57], [10, 0], [-21, -39], [-29, -6], [-2, -19], [-11, -30], [-9, 46], [-10, 25], [-12, -19], [-12, 25], [-11, 3]], [[6157, 6754], [14, 2], [13, 16], [99, 61]], [[6283, 6833], [29, -14], [8, 10], [27, 12], [9, -14], [-11, -23], [36, -19], [5, 12], [20, -9], [21, 6]], [[6459, 6611], [-64, -96], [41, -65]], [[6359, 6325], [-4, 28], [-11, -7], [-25, 17], [-8, 47], [-11, 15], [-5, 41], [-22, 2], [-18, 12], [-2, 42]], [[6253, 6522], [-10, 31], [-20, 7], [-24, -5], [-20, 35], [-13, -14], [-5, 14], [-14, -3], [-17, 11]], [[6130, 6598], [-1, 18], [13, 4], [3, 17], [15, 5], [11, 26], [-17, 12], [8, 50], [-5, 24]], [[6579, 9114], [-11, 38], [-18, 28], [-15, 53], [-66, 89], [-84, 115]], [[6385, 9437], [48, 87], [52, 46], [45, 32], [200, -92], [30, 163], [89, -77], [68, -60], [4, -19], [-15, -39], [-35, -39], [-12, -28], [-6, -63], [-8, -27], [-39, -100], [-13, -11], [-6, -49], [-11, -18], [-31, -83], [-38, 1], [-6, 11], [-23, 14], [-32, 2], [-15, -10], [-32, 0], [-20, 36]], [[107, 7149], [57, 456], [13, -2], [9, 71], [376, -117], [-26, -219], [-17, -120], [-26, -192], [-386, 123]], [[4477, 7911], [2, 30], [19, 3], [24, -14], [46, 4], [25, 32], [35, -10], [43, 49], [20, -25], [13, -44], [30, -15], [-1, 27], [7, 1], [-19, 58], [-9, 17], [-17, 11]], [[4695, 8035], [52, 61], [72, -133], [27, -102], [26, -10], [-29, -74], [-13, -17], [-34, -266], [-296, 103], [22, 75], [-58, 50], [13, 189]], [[7530, 7852], [10, 19], [9, -21], [-15, -19], [-4, 21]], [[7491, 7953], [-1, 10], [27, -23], [-10, -12], [-20, 11], [4, 14]], [[7449, 7733], [14, -14], [-8, -7], [-6, 21]], [[7168, 7897], [17, -7], [-2, 32]], [[7183, 7922], [17, -3], [24, -26], [20, -17], [20, -3]], [[7264, 7873], [-7, -15], [11, -18], [33, 26], [10, -17], [-6, -42], [-33, -18], [-22, -51], [-4, -40], [23, -21]], [[7211, 7552], [-23, -3], [-79, 41]], [[7109, 7590], [-47, 24]], [[6911, 5371], [10, -89], [56, 14], [-4, -19], [6, -16], [10, -73], [-1, -54]], [[6988, 5134], [-3, -1], [4, -98], [-17, -15], [-26, -57], [8, -77], [-105, -26], [-8, 76], [-127, -32], [-27, 234], [-4, 46], [170, 140]], [[2195, 5356], [30, 24], [205, 179], [7, -16], [8, 15], [21, 8], [21, 16], [16, -2]], [[2503, 5580], [16, -1], [14, 10], [47, -4], [0, -15], [14, -15], [40, -408], [-200, -51], [9, -106]], [[2289, 5041], [20, 45], [-4, 46], [-13, 37]], [[2292, 5169], [-23, 42], [-41, 39], [-14, 16], [-18, 43], [-1, 47]], [[7195, 9677], [20, -8], [22, -38], [26, -25], [21, -37]], [[7284, 9569], [20, -14], [48, -8], [22, 2], [43, 21], [23, 21], [27, -6]], [[7467, 9585], [6, -44], [-95, -95], [-64, 34], [-34, -21], [-46, -22], [-21, 25], [-20, -7], [-36, -60], [-39, 93], [-3, 15], [6, 22], [-3, 35], [-11, 11], [-17, 37]], [[4118, 8341], [13, -24], [13, 2], [9, -49], [-5, -6], [14, -41], [52, 44]], [[4214, 8267], [13, -41], [-82, -213], [-36, -67], [14, -18], [-39, -63], [-9, -2], [-12, -21], [-137, 188], [34, 29], [-12, 15], [9, 21], [-8, 17], [-14, -18], [-22, 3], [-1, 24], [-11, 11], [-4, -14], [-15, 13], [0, 28], [9, 11], [-10, 20], [1, 15], [17, 11], [-28, 49], [37, 49], [137, 122], [0, -13], [30, -1], [43, -81]], [[6772, 5860], [14, -1], [0, 54], [34, 75], [65, 5], [25, 22], [61, 21], [11, 16], [13, -7], [15, 5]], [[7010, 6050], [22, -17], [0, -40], [-19, -31], [-8, -53], [-20, -283]], [[6853, 5630], [5, 54], [2, 56], [-30, 27], [-51, 20], [-7, 73]], [[6008, 4006], [-39, -11]], [[5969, 3995], [-59, -18], [-105, -26], [0, 131], [121, 143], [22, 30], [185, 270], [38, -109], [138, -370], [-41, 22], [-227, -52], [-33, -10]], [[7143, 8202], [51, -2], [201, -2], [22, -46], [22, -33], [20, 14], [9, 24], [10, -23], [36, -66], [0, -31], [-28, -16], [-33, -45], [-23, -18], [-40, -2], [-25, -17], [-28, -5], [-17, -17], [-20, 23], [-21, -24], [-15, -43]], [[7183, 7922], [-11, 8], [11, 65], [0, 94], [-40, 113]], [[3041, 8215], [12, 21], [26, -35], [-10, 23], [0, 71], [7, 24], [0, 44], [5, -15], [15, -4], [7, 33], [20, 25], [21, -14], [28, 12], [7, -58], [10, 2], [-4, -89], [-10, -16], [-5, -38], [-15, -32], [-23, -1], [-1, -17], [11, -10], [1, -33], [-25, -69], [8, -37], [-34, 40], [-1, 31], [-14, 37], [-3, 45], [-8, 45], [-26, 6], [1, 9]], [[8126, 2933], [2, -54], [-31, -9], [-10, -29], [-29, -38]], [[8058, 2803], [-27, -13], [-22, 2]], [[8009, 2792], [3, 28], [-8, 34], [-13, 5]], [[7991, 2859], [18, 42], [25, 32], [10, 24], [8, -2], [26, 13], [6, 23], [1, 32], [20, -29], [21, -61]], [[7255, 6675], [27, 18], [-6, -14], [-21, -4]], [[7212, 6672], [4, 19], [6, -26], [-10, 7]], [[7212, 6618], [11, 24], [-4, -30], [-7, 6]], [[7138, 6458], [48, 18], [34, -12], [17, 28], [20, -1], [4, -59], [30, -92], [27, -59], [31, -46], [58, -5], [19, -9], [-5, -10], [-25, 2], [-17, -23], [-28, -13], [-38, -1], [-13, 15], [2, 35], [-27, 42], [-14, 5], [-18, -9], [-15, 26], [4, 18], [19, -15], [19, 2], [-14, 60], [-11, 28], [-1, 30], [-48, 25], [-19, -17], [-15, 22], [-23, 0], [-1, 15]], [[7059, 6365], [7, 11], [20, 4], [18, 27], [1, 34], [17, 6], [8, -25], [-25, -44], [-6, -42], [-15, 15], [-19, -9], [-6, 23]], [[7955, 8479], [15, 16], [19, 72], [19, 27], [-5, 18], [-13, 14], [20, 44], [7, -24], [-5, -15], [6, -15], [20, -12], [11, 17], [17, -8], [26, 8], [4, -21], [-7, -31], [16, -19], [-11, -34], [12, -20], [-8, -28], [-33, -1], [-20, -20], [2, 11], [-21, -31], [2, -15]], [[8028, 8412], [-72, 52], [-1, 15]], [[5230, 8586], [-15, 0], [0, 12], [-22, 13], [-7, 15], [-15, 7], [-7, 20], [-12, -11], [0, 25], [-12, 9], [2, 39], [27, -10], [-3, 38], [13, 24], [28, -23], [25, -50], [13, -6], [26, 5]], [[8304, 3190], [-8, -60]], [[8296, 3130], [-44, 43], [-8, 19], [3, 72], [-7, 47], [-6, 85], [30, 54], [13, -37], [37, -72], [-2, -131], [-8, -20]], [[8058, 2803], [8, -54], [14, 9], [22, -4], [-5, 14], [16, 14], [13, -2], [-20, -84], [-10, -33], [-19, -25], [-20, -14], [-16, 6], [-12, -11], [-29, -3], [-18, -35], [-10, 16], [13, -3], [-2, 37], [-18, 20], [-18, 9], [-33, 3], [-8, -13], [-6, 10], [47, 77], [60, 31], [2, 24]], [[3808, 8717], [8, 27], [15, 14], [3, 20], [-7, 13], [26, 5], [1, 26], [9, -22], [1, 22], [15, -2], [15, 28], [8, 4], [1, -49], [-5, -17], [36, 2], [14, 27], [-22, -72], [-25, -20], [1, -73], [-6, -27], [-10, 0], [-8, 54], [-16, 4], [-30, 48], [-24, -12]], [[7284, 9569], [16, 46], [4, 77], [-9, 0], [-4, 34], [-17, 11], [4, 14], [28, 27], [7, -11], [25, -4], [16, -20], [15, 25], [23, 19], [8, -8], [33, 3], [-3, 15], [8, 19], [-14, 6], [6, 30], [-11, 7], [23, 28], [-13, 17], [18, 7], [-1, -131], [15, -170], [6, -25]], [[6622, 7659], [32, -7], [13, -53], [30, -27], [-3, -60], [-5, -25]], [[6689, 7487], [-3, -78], [-9, -105]], [[6677, 7304], [-10, 5]], [[6667, 7309], [-56, 25], [-43, 27]], [[6568, 7361], [28, 126], [-7, -1]], [[9676, 2660], [23, -24], [28, 16], [7, -4]], [[9734, 2648], [-14, -36], [-2, -34], [-72, -20], [-10, -12], [-30, 10], [-31, -6]], [[9575, 2550], [-1, 43], [-15, 10], [8, 29], [16, 21]], [[5826, 5671], [14, 14], [33, 19], [17, -6], [13, -25], [27, 33], [12, 2], [-13, -37], [-17, -25], [11, -71], [28, -13], [-7, -23], [-44, -66], [-11, 48], [0, 23], [-16, -37], [-10, 24], [-11, 50], [-24, 20], [-5, 23], [7, 4], [-8, 35], [4, 8]], [[2458, 7044], [-19, -2], [0, 19], [-11, 37], [-1, 27], [8, 21], [18, 2], [6, -13], [26, 9], [15, -25], [27, -4], [13, -35], [3, -23], [-8, -45]], [[9637, 2918], [42, -10], [21, 12], [14, 17], [20, -16], [11, 2], [10, 21], [96, 5], [9, -21], [-13, -77], [-38, -54], [-21, -22], [-41, 0], [-13, -127]], [[9603, 2811], [-13, 38], [6, 2], [26, 38], [13, -2], [2, 31]], [[7517, 8449], [17, 7], [15, 14], [5, 44], [16, 27], [16, 14], [23, -5], [3, -56], [-6, -23], [1, -60], [-3, -36], [-19, 29], [-8, -13], [1, -35], [-33, 33], [-24, 18], [-4, 42]], [[8422, 3078], [29, -10], [12, 20], [26, -15], [11, 43], [18, -16], [5, 7], [99, -59], [88, -30]], [[8710, 3018], [-38, -83], [-45, -94]], [[8627, 2841], [-19, 29], [-51, 62], [-16, 12], [-46, 19], [-45, 36], [-30, 11], [-28, 4]], [[8392, 3014], [-5, 24], [16, 12], [16, -10], [3, 38]], [[6230, 4816], [78, 63], [-7, -22], [10, -6], [-20, -13], [6, -10], [12, -59], [-18, -15], [51, -115], [-17, -2], [-21, 9], [-3, -39], [-22, 14], [-17, 22], [-4, 46], [-10, 33], [-18, 94]], [[581, 8888], [-1, -18]], [[580, 8870], [-30, 7], [-14, 16], [-5, -142], [-21, 1], [-14, 11], [14, 68], [-8, -1], [-16, 24], [-11, 43], [10, 49], [-28, -17], [-7, 12], [3, 20], [-11, 3], [3, 44], [25, 12], [16, 21], [16, -13], [0, -19], [22, 0], [12, -16], [21, -78], [24, -27]], [[2392, 8329], [23, -43], [3, -43], [18, -8], [18, -22], [12, -23], [-27, -5], [-56, 1], [-12, 25], [-23, 2], [-21, -30], [-12, -5]], [[2315, 8178], [-7, 14], [2, 28], [17, 15], [19, 43], [35, 44], [11, 7]], [[9068, 2861], [5, 0], [41, 62], [17, 10]], [[9131, 2933], [17, -4], [12, 22], [17, -23], [7, 5], [4, -22], [14, 18], [17, -12], [21, 6], [14, -16], [-4, -19], [40, -35]], [[9290, 2853], [17, -23], [-10, -21]], [[9297, 2809], [-30, -7], [-25, 4], [-36, -22], [-16, -26], [-2, -13], [16, -31], [-21, -4], [-22, -12], [-5, 40], [-11, 10], [-30, 12], [-35, 4], [-10, 8]], [[9070, 2772], [-4, 45], [-7, 10], [9, 34]], [[9899, 2722], [6, -24], [15, -11], [-7, -5], [7, -18], [-7, -13], [-20, -4], [-37, -49], [1, -13], [36, -39]], [[9893, 2546], [-13, -35], [-10, 10], [-32, 55], [-44, 32], [-7, 33], [7, 39], [16, 3], [-2, 15], [9, 39], [15, 18], [23, -3], [28, -14], [16, -16]], [[8049, 3935], [29, 50], [8, -9], [10, 17], [11, -33], [-2, -67], [-19, -44], [-10, 0], [-17, 28], [-10, 58]], [[3646, 7195], [31, -11], [0, 41], [-6, 31], [4, 9], [28, -4], [27, -92], [-5, -46], [5, -12], [-8, -26], [-21, 23], [-7, 24], [-20, -3], [-21, 30], [-7, 36]], [[8022, 2269], [-7, 6], [1, 41], [-11, -29], [-17, 13], [-14, -2], [-12, 14]], [[7962, 2312], [2, 5], [-15, 54], [-23, 33], [7, 44], [18, 4], [17, 15], [24, 6], [17, 33], [-3, 13], [36, 4], [32, -20], [-10, -83], [-42, -151]], [[7266, 7517], [-19, -52], [-3, -34], [-20, -24], [-21, 21], [-17, -9], [-2, 24], [-40, -1]], [[7144, 7442], [-35, 148]], [[7677, 5860], [22, -11], [11, -25], [40, 10], [-7, -40], [-1, -36], [-8, -31], [12, -51], [1, -48], [9, -12], [-6, -34]], [[7750, 5582], [-18, 23], [-13, 4]], [[7719, 5609], [-4, 19], [-15, -1], [-9, 32], [-24, 25], [-27, -3], [-14, 19], [-37, 100]], [[7589, 5800], [27, 15], [23, 2], [44, -8], [-6, 51]], [[581, 8888], [2, 50], [27, -3], [202, -13], [108, -8], [-11, -327], [-113, 12], [-197, 22], [5, 161], [-27, 2], [3, 86]], [[2220, 6344], [22, -8], [13, -22], [7, -80], [-4, -18], [-23, -30], [-30, -74], [-17, -88], [8, -26], [25, -26], [8, -41], [23, -32], [26, -8]], [[2278, 5891], [8, -29], [-3, -37], [-43, -59], [-50, -37], [-8, -21], [-6, -38], [-2, -56], [4, -26]], [[2178, 5588], [-168, 5]], [[2010, 5593], [-5, 125]], [[2005, 5718], [1, 35], [-12, 145], [60, 21], [6, 55]], [[5256, 6858], [118, 27]], [[5374, 6885], [157, 33], [-23, -167]], [[5498, 6610], [-62, -13], [-24, 15], [-101, -24], [-52, -37], [-47, -57], [-21, 43], [-15, 20], [-22, 54], [1, 41], [-39, 35], [-22, 43], [46, 47], [19, 61], [97, 20]], [[6689, 7487], [25, -14], [24, 5], [0, 10], [23, 11]], [[6761, 7499], [25, -62], [55, -128]], [[6841, 7309], [-166, -36], [2, 31]], [[6530, 7129], [18, 15], [-11, -27], [24, -38], [18, -12], [2, -17], [12, -16], [30, -20], [12, 25], [10, -8], [22, 10], [28, -26]], [[6695, 7015], [8, -29]], [[6704, 6875], [-23, 4], [-66, 0], [-44, 84], [4, 10], [-12, 25], [-6, -7], [-33, 71]], [[6138, 7185], [162, -111]], [[6300, 7074], [25, -15], [4, -21], [15, -36], [-5, -11], [11, -40]], [[6350, 6951], [-67, -118]], [[6157, 6754], [-15, 12], [-23, 63], [9, 23], [-16, 38], [24, 86], [-25, 18], [-9, 35], [-10, 5], [5, 19], [-13, 9], [12, 49], [21, -14], [21, 88]], [[6703, 7115], [0, 11], [34, 6], [32, 43], [65, 8]], [[6834, 7183], [-14, -59]], [[6820, 7124], [-15, -58], [-29, -50], [-14, -2], [9, -18], [-15, -38]], [[6695, 7015], [0, 19], [14, 44], [-7, 15], [1, 22]], [[5806, 8588], [9, 35], [28, 7], [33, -44], [168, 72], [34, -98], [6, -5], [16, 30], [14, 12], [12, -76], [-10, -91], [-9, -50], [-16, -32], [-37, -17], [0, 12], [-67, -6], [-2, -42], [-11, 5], [-6, 34], [-9, 4], [-90, 74], [-14, 71], [-28, 11], [-8, 20], [-13, 74]], [[6350, 6951], [15, -31], [28, -5], [30, -14], [43, -16]], [[6466, 6885], [31, 1], [11, -10], [-10, -53]], [[8028, 8412], [-7, -17], [-19, -11], [-15, -28], [0, -54], [-10, -47], [-17, -34], [-13, -15], [-6, -28], [-19, -33], [-30, -11], [-3, 23], [18, 49], [8, 38], [-5, 31], [-20, 34], [-32, -10], [0, -25], [-14, -15], [-9, -28], [11, -17], [-21, -46], [-15, -11], [-16, -40], [-28, -11], [-7, -20], [-15, -1], [1, 23], [-6, 34], [-49, 39], [-19, 12], [-49, 184], [52, 136], [42, 137], [17, -8], [40, -33], [29, -15], [13, 0], [27, 38], [25, 48], [20, 16], [9, 31], [54, 71], [14, 0], [-11, -151], [2, -168]], [[6883, 7655], [29, 32], [18, -8], [20, 22], [-12, 19], [17, -3]], [[7144, 7442], [-17, -35], [-22, -26]], [[7085, 7373], [-14, 6], [-39, -61], [-1, -15]], [[7031, 7303], [-23, 4]], [[7008, 7307], [-31, 39], [-13, 10], [12, 23], [-10, 15], [-12, -8], [-6, 18], [-17, 88], [-23, 132], [-25, 31]], [[8710, 3018], [24, -6], [168, -20], [79, -8], [18, -29], [27, -20], [9, -30], [25, -43], [8, -1]], [[9070, 2772], [2, -43], [-18, -114]], [[9054, 2615], [-26, -163], [23, -57], [16, -48], [-18, 0], [-10, -11]], [[9039, 2336], [-10, 31], [-20, 14], [-27, 0], [-28, -17], [-2, -17], [-32, -13], [-14, -12], [-14, 30], [-25, 26], [-24, 9], [-40, -9], [-25, -22], [-14, -26], [1, -19], [-15, -47], [-27, -29], [-62, -29], [-24, 5], [-53, -16], [-30, 3], [-16, -38], [-11, -52], [-11, -17]], [[8516, 2091], [-2, -2]], [[8480, 2127], [-6, 19]], [[8515, 2268], [5, 35], [-11, 77], [-34, -14], [-10, 8], [4, 19], [23, 1], [12, 12], [23, 67], [-13, 39], [-23, 45], [136, 284]], [[6820, 7124], [20, -51], [16, -5], [0, -11], [33, -15], [-12, -22]], [[6801, 6464], [-5, -19], [29, -11], [21, 2], [15, -19], [12, 28], [-1, 24]], [[6892, 6462], [2, -17], [20, -2], [30, 34], [11, -11], [-3, -14], [-23, -10], [-25, -19], [2, -25], [-14, -19], [-36, -33], [16, -41], [56, -52], [13, -33], [26, -1], [27, -17], [18, 32], [32, 15], [6, 25], [-10, 32], [11, 5], [14, -51], [-7, -70], [-8, -50]], [[7050, 6140], [-20, -41], [-13, 5], [-9, -39], [2, -15]], [[6772, 5860], [-71, -15], [-25, 0]], [[6676, 5845], [-32, 60], [59, 45], [58, 49], [-22, 78], [64, 74], [22, 28], [-30, 44], [-3, 65]], [[2178, 5588], [-2, -45], [3, -21], [25, -46], [10, -37], [-3, -25], [-16, -58]], [[2292, 5169], [-6, -5], [-23, 6], [-7, -45], [-27, 16], [-31, -6], [-26, 24], [-5, 52], [-24, -7], [-19, 2], [-35, -17], [-8, -24], [0, -35], [-5, -16], [-12, 17], [-6, 26], [-13, 21], [-10, 36], [-17, 5], [-1, 30], [-7, 3], [-29, -5]], [[1981, 5247], [6, 40], [8, 99], [11, 43], [-1, 47], [-7, 16], [10, 51], [2, 50]], [[1859, 6331], [-4, 169], [-9, 309], [294, 77], [11, -83], [1, -34], [7, -30], [-15, -25], [3, -18], [39, -5], [11, -9], [9, -33], [42, -40], [47, -16], [9, -19], [-6, -31], [-20, -14], [-18, -54], [-34, -73], [-10, -34]], [[6555, 3181], [17, -13], [6, 6], [311, -117], [-7, -210], [-159, -160], [-115, 45], [-26, 0], [-14, -81]], [[6568, 2651], [-39, -262], [-3, -47]], [[6526, 2342], [-5, -19], [-8, -133], [-7, 7], [-2, 68], [3, 47], [14, 28], [8, 193], [-126, 48], [0, 21], [-57, 22], [-16, 40]], [[6330, 2664], [33, 59], [45, 66], [17, 38], [30, 78], [51, 106], [26, 65], [1, 49], [22, 56]], [[6985, 3741], [-18, -20]], [[6967, 3721], [-9, -7], [-63, -95], [-82, 76], [-107, 114], [-12, 20], [-50, -4], [-28, -5], [-6, -48], [-11, -58], [-17, 6], [-18, 19], [-6, 49], [-22, 11], [-1, 12], [-163, 56], [-21, 191], [113, 169], [84, 171], [74, 162], [41, -14], [5, -52], [14, -30], [-9, -71], [9, -37], [-9, -31], [-8, -50], [-19, -44], [85, -217], [23, -15], [6, 22], [16, 0], [19, -58], [-16, -10], [7, -13], [-11, -13], [2, -13], [17, -19], [10, 11], [3, -14], [11, 17], [24, 0], [35, 38], [14, -11], [15, -46], [25, 13], [8, 27], [-6, 44], [-16, 0], [20, 58], [16, -3], [30, -187], [10, -88], [-8, -13]], [[7050, 6140], [4, -24], [28, 21], [17, 34], [29, 9], [7, 24], [-4, 40], [27, 16], [22, -25], [4, -23], [-27, -4], [1, -51], [-45, -17], [4, -51], [16, -46], [9, -45], [-3, -21], [25, -5], [-12, -192], [-17, -220]], [[7135, 5560], [-46, -38]], [[7089, 5522], [-118, -96]], [[2315, 8178], [8, -75], [-4, -23], [-36, -9], [-10, -22], [-12, 8], [-11, 26], [-17, -11], [-45, 3], [-17, 49], [-59, -10], [33, 281], [17, 135], [138, 34], [94, 24], [37, 4], [-2, -41], [3, -23], [-16, -4], [-9, -20], [6, -36], [-13, -32], [6, -76], [-14, -31]], [[8111, 3066], [8, -24], [7, -59], [0, -50]], [[7991, 2859], [-26, 22], [-11, 2], [12, 62], [20, 35], [0, 25]], [[9489, 3125], [3, 20], [55, 35], [38, 15], [31, 25], [24, -2], [62, 49], [3, -44], [-44, -55], [-35, -52], [-6, -23], [-11, 1], [-40, -33], [-30, 29], [-37, -33], [-13, 68]], [[9899, 2722], [31, 16], [11, 19], [17, -25], [6, 20], [4, -16], [3, -52], [6, -2], [9, -38], [13, 3], [-8, -56], [-20, -46], [-16, 17], [-8, -3], [-6, -24], [-19, 23], [-29, -12]], [[8159, 2033], [13, 3], [4, 35], [25, 18], [19, 59], [25, 32], [29, -63], [-6, -53], [-8, -19], [31, 6], [-2, -20], [-20, -52], [-1, -26], [-21, -52], [-15, -22], [1, -10], [-33, -16], [-43, -9], [-19, -16]], [[8281, 2686], [22, 2], [0, 31], [11, 25], [16, -21], [29, 83], [27, -15], [-6, -39], [38, 28], [10, -37], [7, -58], [-56, -10], [2, -34], [8, -8], [-1, -27], [-8, -10], [-42, 33], [-6, -13], [-7, -44], [-25, -2], [-1, 18], [-17, -2], [1, -12], [-22, 31], [20, 81]], [[9765, 3311], [-4, 8], [21, 40], [19, 28], [11, 5], [34, -16], [17, 23], [22, -58], [-15, -30], [-8, 0], [1, -37], [-9, -13], [-20, -3], [-7, 6], [-25, -30], [-10, 42], [-17, 16], [-10, 19]], [[9203, 4877], [37, 36], [38, 46], [23, 23], [50, 21], [32, -2], [17, -8], [-1, -23], [-24, 12], [-41, -16], [-26, -21], [-24, -36], [-27, -88], [-10, 19], [-28, 11], [-16, 26]], [[8304, 3190], [11, -12], [34, -4], [10, 4], [5, 24], [-4, 23], [28, 17], [0, -17], [54, -61], [-12, -5], [8, -16], [-10, -16], [-6, -49]], [[8392, 3014], [-34, 11], [-20, 24], [-22, 54], [-20, 27]], [[9290, 2853], [13, 19], [34, 26]], [[9337, 2898], [7, -45], [36, -2], [-4, 37], [-8, 33], [42, 10], [10, 9]], [[9420, 2940], [18, -127]], [[9438, 2813], [15, -98]], [[9333, 2734], [0, 2]], [[9333, 2736], [-1, 21], [-35, 52]], [[9163, 2667], [-1, 12], [65, -2], [-8, 12], [77, 31], [-3, 5], [40, 11]], [[9265, 2461], [-14, -25], [-26, -10], [-39, -39]], [[9186, 2387], [-3, 7], [4, 47], [-9, 24], [4, 13], [-7, 23], [-11, -13], [-5, 15], [3, 43], [-5, 10], [10, 44], [-4, 67]], [[6909, 8030], [15, 26], [2, 23], [10, 16], [1, 25], [8, 15], [-3, 30], [16, 28], [-1, 11], [34, 17], [57, 65], [65, 48], [9, -26], [-13, -57], [19, -45], [15, -4]], [[7349, 8779], [14, 3], [3, 21], [13, -16], [15, 1], [9, -29], [35, 28], [18, -24], [4, -22], [-9, -23], [17, -14], [-17, -35], [-9, 12], [-29, 11], [-7, 17], [-13, -4], [-3, -20], [-11, 10], [-1, 18], [-17, -5], [-7, 21], [8, 22], [-14, 15], [1, 13]], [[6811, 7676], [72, -21]], [[7008, 7307], [-9, -10], [-10, -35], [-21, -35], [-23, 22], [-20, -23], [-22, -8], [4, 18], [-24, 20], [6, 32], [-9, 11], [-17, 39], [-22, -29]], [[6841, 7309], [0, 0]], [[6761, 7499], [2, 61], [21, 16], [16, 42], [-12, 32], [23, 26]], [[7089, 5522], [12, -93]], [[7101, 5429], [15, -119], [46, -99], [-90, -33], [-84, -44]], [[7777, 4431], [-29, 45], [-10, 53], [-18, 11], [-10, -7], [-25, -1], [2, 11], [-31, 17], [-36, 25], [-5, -10], [-12, 19], [-13, -12], [-29, 10], [12, 25], [12, 69], [24, -29], [24, -39], [3, 37], [10, 33], [11, -32], [29, -6], [8, 22], [13, 14], [18, -65], [32, -1], [3, -22], [11, 8], [19, -15], [3, -68], [16, -24]], [[7573, 2829], [8, 2], [1, 32], [28, 44], [10, -23], [2, -35], [-15, -1], [-7, 12], [-3, -19], [10, -33], [13, -1], [16, -58], [-14, -6], [12, -22], [-8, -15], [-14, 8], [-11, 36], [-20, 15], [0, 59], [-8, 5]], [[6985, 3741], [19, 18], [15, 24], [20, 43], [44, 18], [21, 20], [35, 12]], [[7139, 3876], [21, -25]], [[7160, 3851], [0, -26], [9, -16], [-9, -12], [5, -33], [-12, -63], [-24, 1], [-9, -11], [0, -24], [-19, -22], [-18, 14], [-1, 13], [-17, -24], [-30, 46], [-46, 27], [-22, 0]], [[7589, 5800], [-50, 91], [-33, 39], [23, 27], [1, 18], [26, -7], [7, 8], [22, -2], [15, -11], [17, 11], [13, -2], [11, -32], [11, -9], [0, -18], [12, -39], [13, -14]], [[7953, 5078], [-12, 43], [-28, 16]], [[7913, 5137], [-18, 20], [-7, 20]], [[7888, 5177], [10, 31], [-15, 15], [-18, -24], [-10, 0], [-6, 55], [-6, 8]], [[7843, 5262], [10, 29], [2, 26], [-16, 47], [11, 6], [45, -109], [69, -119], [5, -43], [-16, -21]], [[7929, 4463], [15, -30], [4, -25], [-22, 51]], [[7871, 4410], [55, -97], [-3, -46], [-7, -21], [0, -36], [-30, 21], [-24, 33], [-14, 46], [-16, 36], [-21, 30]], [[5068, 7940], [42, 25], [26, 7], [-3, 32], [-8, 1], [-29, 45], [-5, 22], [49, 45], [24, -12], [20, -53]], [[5184, 8052], [-17, -24], [1, -18], [-12, -18], [27, 5], [13, -18]], [[5196, 7979], [-7, -67], [-17, -129], [-23, -34], [-63, 18], [-10, 24], [-7, -12], [-14, 41], [7, 34], [-29, -8], [-3, 15]], [[5207, 8370], [8, -2], [16, -27], [19, 11], [10, 25], [16, 0], [6, -33], [19, -14], [-7, -28], [-22, -15], [17, -16], [0, -23], [-12, -9], [-13, 20], [-9, -23], [-19, -1], [-13, 26], [-2, 49], [-12, 10], [-2, 50]], [[5256, 6858], [8, 32], [-11, 56], [-13, -17], [-15, -38], [-21, 37], [23, 30], [-71, 64], [55, 57], [77, 31], [42, -31], [-7, -35], [21, -49], [-8, -23], [10, -47], [16, -7], [12, -33]], [[6138, 7451], [16, 49], [15, 14], [13, 40], [32, 30]], [[6214, 7584], [84, -144], [5, 26], [18, -28]], [[6364, 7339], [11, -28], [23, -30], [-13, -24]], [[6326, 7126], [-26, -52]], [[6138, 7185], [3, 33], [-15, 129]], [[6126, 7347], [-4, 53], [16, 51]], [[4806, 8696], [27, -14], [3, 9], [-29, 39], [-1, 24], [26, -9], [18, 6], [25, -23], [6, -25], [10, 17], [24, 16], [-3, -55], [-15, -4], [9, -27], [7, -51], [-14, 8], [-25, 34], [-15, 13], [-18, -18], [9, 24], [-45, 33], [1, 3]], [[6568, 7361], [-14, -58], [6, -25], [-15, -4], [-8, -21], [-58, 1]], [[5461, 5231], [12, 9], [8, 21], [58, 35], [22, 1], [19, 14], [8, 31], [8, -12], [-14, -72], [3, -36], [-6, -28], [25, 2], [2, -27], [-7, -58], [-34, -12], [-6, -20], [-19, -18], [-24, 7], [-21, -40], [-10, 17], [-20, 18], [1, 115], [7, 29], [-12, 24]], [[6533, 5990], [-23, -14], [-8, -30], [0, -41], [-11, -30], [-61, 88], [-56, 30], [-64, 98], [-69, 88]], [[6241, 6179], [6, 30], [17, -8], [12, 6], [5, 30], [20, -8], [23, 0], [18, 9], [26, 70]], [[6044, 6241], [-3, -14], [26, 2], [33, -43], [23, 12], [2, -20], [14, -24], [6, 1], [-2, 29], [26, -31], [23, 7], [8, 19], [15, 1]], [[6215, 6180], [-3, -11], [5, -39], [-34, -43], [-7, 27], [-14, 10], [-7, -30], [4, -16], [-16, -71], [-7, -8], [0, -25], [-26, -33], [-15, 21], [4, 73], [-4, 19], [-13, 8], [-1, 34], [-34, 2], [5, 44], [-10, 77], [2, 22]], [[5943, 5750], [54, 120], [5, 15], [7, -12], [2, -27], [15, -25], [30, 8], [-7, -21], [22, -26], [27, 26], [33, 15], [-10, -65], [-12, 9], [-10, -6], [-6, -50], [-6, -22], [6, -29], [21, -36], [0, -11], [-23, 24], [-4, -9], [-30, 12], [-16, 19], [-27, -42], [-26, 43], [2, 24], [-43, 68], [-4, -2]], [[6115, 5449], [39, 25], [34, 41], [4, 13], [15, -9], [10, -21], [9, 3], [31, -20], [21, -26], [11, 0], [-44, -45], [-9, -26], [6, -31], [-25, -17], [-17, 30], [-8, -23], [-22, 27], [5, 35], [-12, 34], [-7, -16], [-41, 26]], [[3514, 5045], [11, -2], [8, 37], [22, 7], [24, -24], [-18, -39], [10, -28], [32, -14], [8, 3], [0, -62], [-25, 8], [6, -52], [-9, -68], [5, -25], [-20, 0], [-9, 20], [-21, 5], [-6, 15], [-17, 7], [19, 67], [6, 39], [-5, 44], [-21, 62]], [[2634, 5459], [27, 7], [12, 14], [-4, 40], [10, -7], [51, -7], [12, 15], [38, 8], [16, -11], [7, -15], [8, -61], [-4, -15], [-4, -113], [2, -37], [-33, 13], [-25, 35], [-20, -4], [-2, 20], [-42, -5], [2, 24], [-13, 30], [-38, 69]], [[5184, 8052], [15, 6], [9, 22], [35, -7], [5, -20], [-14, -58], [19, -7], [19, 6], [-32, -38], [-44, 23]], [[6240, 7684], [29, 115], [12, -7], [16, 55]], [[6297, 7847], [22, 69]], [[6319, 7916], [28, -54], [7, -7], [66, -114]], [[6214, 7584], [26, 100]], [[7135, 5560], [33, 26], [5, -38], [-50, -28], [0, -23], [7, -33], [-29, -35]], [[9211, 186], [1, 7], [33, 5], [0, -9], [24, 39], [1, 31], [-12, 25], [9, 30], [16, -7], [70, -1], [-3, -31], [-10, -31], [-25, -16], [10, -3], [-5, -20], [-12, -5], [-19, -28], [-31, -31], [-50, 40], [3, 5]], [[9462, 87], [17, 28], [-11, 39], [4, 20], [17, 23], [-13, 10], [11, 9], [-9, 12], [2, 23], [-11, 52], [39, 9], [15, 12], [28, 2], [38, -59], [-12, -55], [-11, -23], [17, -11], [-6, -14], [41, -2], [75, -21], [-7, -39], [-17, -15], [-11, 12], [-19, 4], [-6, -32], [-35, -5], [-6, -17], [-4, 24], [-8, -44], [-37, 63], [-7, 22], [-11, -7], [-8, -20], [-27, -37], [-28, 37]], [[4886, 5290], [16, 43], [10, 0], [16, 22], [29, 17], [2, 38], [27, -8], [14, 12], [17, -32], [2, -22], [10, -16], [-8, -20], [12, -30], [-8, -22], [-19, -23], [26, -57], [-11, -10], [-84, 48], [-16, 24], [-16, -11], [-19, 47]], [[9438, 2813], [108, 60], [7, 51], [27, 9], [27, -24], [30, 9]], [[9575, 2550], [-8, -2], [-82, -45]], [[6472, 7042], [-18, -38], [2, -46], [-7, -5], [12, -35], [5, -33]], [[6240, 7684], [-14, 32], [-9, 50], [-8, 1], [-20, 32], [2, 30], [-11, 60], [0, 27], [16, 13], [-4, 27], [5, 16], [17, 6], [14, -14], [19, -42], [19, 20], [31, -95]], [[601, 8037], [3, 12], [34, -9], [6, -6], [-7, -30], [-13, -24], [-7, 2], [-17, 33], [1, 22]], [[2219, 7934], [7, 6], [3, 47], [-3, 42], [4, 10], [53, -60], [3, -78], [-23, -62], [-18, -20], [-19, 22], [9, 37], [-4, 18], [-11, 6], [-1, 32]], [[1265, 5735], [37, 14], [27, -43], [10, -24], [23, -28], [26, -8], [0, -9], [-88, 5], [-35, 93]], [[3658, 5948], [14, -16], [15, 21], [9, -5], [25, 3], [22, -30], [14, -37], [-21, -15], [-13, -2], [-67, 38], [2, 43]], [[3227, 8259], [14, -3], [10, 20], [16, 10], [-4, 39], [47, 17], [24, 1], [7, 10], [26, 2], [0, -32], [7, -49], [10, 1], [2, -34], [7, 0], [-6, 27], [6, 19], [13, 13], [13, -3], [22, 18], [-1, 35], [-6, 34], [45, 11], [-20, -40], [-5, -63], [-14, -30], [-16, -21], [-2, -16], [-27, -52], [24, -30], [-6, -19], [-6, 19], [-12, -13], [-3, 23], [-8, 1], [-2, -34], [-13, 0], [-1, -69], [-38, 6], [-20, -21], [-13, 0], [1, 39], [-10, 63], [-8, 4], [-20, -22], [-4, -14], [-13, 2], [-16, 151]], [[5316, 6222], [19, 5], [-9, 35], [135, 75], [-18, -75], [-1, -51], [-4, -2], [-22, 23], [-29, -12], [-19, 2], [-30, -13], [-22, 13]], [[5313, 5485], [41, -48], [31, -50]], [[5385, 5387], [-13, -50], [-8, -15], [10, -18], [-19, -25], [-17, 43], [-24, 26], [-11, 32], [-19, 28], [20, 19], [29, -12], [0, 11], [-22, 55], [2, 4]], [[4732, 8238], [9, 68], [53, 13], [41, -70], [18, -1], [8, -14], [8, -43], [7, -15], [1, -30], [-34, -2], [-4, -18], [4, -29], [-19, -11], [-17, 47], [-16, 30], [-7, -21], [-14, 44], [-27, -19], [-16, 58], [5, 13]], [[5313, 5485], [-37, 51], [7, 15], [-10, 62], [11, 24], [20, -14], [13, 2], [16, -13], [17, 4], [19, 20], [3, 17], [47, -21], [33, -10], [43, -57], [28, -25], [-1, -138], [-33, -42], [-33, -48], [-14, 13], [-9, 31], [-29, 1], [-19, 30]], [[3882, 5282], [4, -46], [-17, -5], [-19, -122], [-16, -3], [-6, -23], [1, -44], [-17, 1]], [[3812, 5040], [-12, -1], [-33, 37], [2, 32], [11, 38], [-10, 28], [0, 18], [-16, 0], [5, 47], [13, 56], [50, 26], [22, 45], [28, 22], [10, -106]], [[3401, 5914], [16, -9], [1, 15], [15, -5], [16, 26], [10, 37], [20, 7], [6, -17], [26, 4], [-30, -50], [-13, -39], [-9, -11], [-6, -45], [-16, 8], [-2, 21], [-14, 3], [-4, 33], [-16, 22]], [[2159, 6781], [18, 14], [-13, 60], [9, 1], [2, -21], [12, -18], [12, 3], [1, 14], [26, 21], [8, 19], [-6, 67], [8, 21], [18, -24], [4, 20], [11, 7], [5, 41], [8, 6], [11, -48], [-15, -69], [1, -38], [6, -34], [-22, 6], [-7, -23], [-21, -29], [-1, 52], [-18, -23], [5, -28], [-12, -14], [-46, -2], [-4, 19]], [[3361, 6094], [-76, -19], [-31, -75], [-31, -2], [-8, 41]], [[3215, 6039], [-11, 39], [23, 34], [9, 5], [-10, 16], [-9, 45], [-10, 29], [23, 27], [20, 42], [15, 10], [29, -12], [12, -31], [23, -4], [14, 11], [4, -23], [21, 12], [3, 38], [7, -1], [-7, -30], [5, -85], [14, -4], [2, -51], [-22, 9], [-9, -21]], [[7888, 5177], [-10, -9], [-5, -24], [-18, 10], [-3, 17], [-24, -5], [-4, -16], [-17, -17], [-13, -45], [6, -17], [12, -8], [4, -24], [-11, -22], [-11, 13], [-117, 127], [19, 19], [24, -2], [-33, 75], [48, 34], [24, -4], [14, 9], [23, -15], [-1, -12], [-19, -60], [-15, -6], [9, -18], [12, -1], [19, 23], [1, 36], [31, 2], [10, 25]], [[6322, 4442], [8, 20], [8, -7], [7, 28], [13, 15], [19, -48], [10, 23], [17, 21], [15, -23], [23, -59], [-35, -21], [-17, 18], [-3, -13], [-16, -7], [-2, 11], [-13, -20], [-18, -12], [-16, 74]], [[6263, 2947], [20, 9], [5, 24], [16, 18], [20, -4], [-4, -26], [14, -5], [-3, -41], [-6, -27], [-13, 0], [-10, 15], [-40, 29], [1, 8]], [[7000, 2498], [5, -35], [27, -51], [5, -33]], [[7037, 2379], [-27, -13], [13, -63], [-49, -17], [-4, 23], [10, 38], [-4, 24], [-12, 35], [-8, 0], [-13, -32], [-42, 3], [-3, 39], [-22, -4], [-17, 42], [-11, 13], [-33, -3], [-19, -11], [5, 32], [21, 11], [2, 16], [96, -11], [80, -3]], [[2731, 6245], [11, 60], [27, 24], [-4, 22], [3, 47], [14, 32], [39, -68], [22, -11], [26, -19], [20, -7], [-2, -44], [4, -28], [11, -14], [0, -23], [-8, -14], [-6, -33], [-27, -33], [-8, -50], [-8, -17], [-5, 33], [0, 32], [-14, 14], [3, 36], [-7, 15], [7, 22], [-13, 49], [-26, -35], [-39, 2], [-20, 8]], [[6330, 2664], [-21, 54], [49, 246], [12, 40], [2, 23], [-10, 21], [12, -2], [86, -31], [3, 68], [3, 130], [4, 107], [97, 10], [15, -75], [-8, -30], [-19, -44]], [[4064, 6753], [19, 16], [9, 49], [16, 107], [19, -2], [7, -32], [24, 18], [23, 0], [21, -20], [3, -22], [22, -2], [-26, -36], [-16, 10], [-24, -4], [12, -36], [-25, -24], [-14, 26], [-15, 11], [4, -47], [-4, -25], [9, -33], [-25, -1], [-23, -25], [-14, 33], [-2, 39]], [[9801, 3850], [7, 26], [3, -16], [19, -11], [18, -2], [14, 9], [10, -66], [-8, -61], [-1, -44], [7, -23], [-4, -25], [6, -47], [-39, -16], [4, -32], [-14, -10], [-9, -39], [0, 128], [-13, 229]], [[8022, 2269], [-18, -67], [-8, -102], [6, -55], [26, -58], [-34, 33], [-15, -8], [-17, 17], [-4, 37], [-30, 132], [2, 31], [15, 20], [2, 38], [15, 25]], [[5664, 7262], [63, 198], [35, -13], [26, -19], [34, -63], [-10, -26], [3, -11], [-28, -9], [-7, -23], [-22, 2], [-33, -10], [-5, -28], [-23, -18], [-33, 20]], [[6988, 8510], [44, 47], [-8, 45], [31, -25], [8, -35], [11, 21], [29, -7], [-18, -83], [15, -61], [-6, 4], [-29, -8], [-15, 26], [-19, 11], [-20, -29], [-11, 8], [-10, 42], [4, 13], [-6, 31]], [[3038, 5146], [25, 37], [12, 45], [-13, 25], [-3, 19], [25, -8], [23, 21], [22, 0], [8, 8], [25, 4], [3, -28], [14, -23], [0, -28], [-15, -41], [-3, -36], [-25, -10], [-11, -21], [-23, 19], [-2, -14], [-17, 2], [2, 26], [-44, -6], [-3, 9]], [[5462, 7837], [27, 71], [17, 24], [46, 28], [70, -83], [-10, -26], [-17, -3], [-17, -28], [1, -25], [-16, -39], [-13, -7], [-43, 46], [-24, 18], [-21, 24]], [[1981, 5247], [-32, -153]], [[1949, 5094], [-381, 130], [-6, 58], [-43, 19], [8, 59], [24, 11], [-1, 36], [21, 12], [0, 18], [21, -1], [47, 115], [15, 8], [14, 34], [13, 19], [36, 210], [56, -20], [232, -84]], [[5593, 4871], [-2, 173], [5, -1], [5, 68], [16, 119], [7, 86], [4, 87], [4, 20], [19, -1], [13, 26], [44, -5], [3, -27], [18, 6], [16, 28], [15, -12], [39, -13], [10, -14], [-5, -20], [42, -137], [24, -108], [-17, -81], [-67, -213], [-197, -38], [4, 57]], [[2659, 8811], [15, 64], [-4, 20], [21, 47], [-2, 28], [21, 0], [34, 15], [12, 36], [49, -3], [22, -114], [-37, -11], [-13, -24], [-44, -22], [-10, -14], [-15, -62], [-15, 4], [-30, -16], [-4, 12], [0, 40]], [[7722, 3061], [-28, -42], [-3, -15], [26, -25], [-5, -4], [16, -31], [0, -27], [-17, 4], [-7, 15], [-27, 30], [-12, -5], [-2, 31], [-9, 16], [5, 93], [8, 19], [8, -3], [-6, -25], [12, -19], [10, 27]], [[2392, 6199], [14, 1], [29, -17], [18, 37], [3, 39], [30, 24], [10, 30], [21, -7], [16, -21], [-6, -11], [18, -3], [13, -20], [-5, -16], [3, -34], [-32, -13], [-1, -28], [-8, -38], [-21, 29], [-10, 4], [-27, -11], [-36, -39], [-24, 12], [-6, 37], [1, 45]], [[4342, 5441], [40, 43], [14, -11], [-2, -40], [15, 7], [-5, -76], [4, -4], [9, -49], [9, -1], [-4, -64], [-11, -47], [-16, -3], [-16, -58], [-12, 17], [-14, 2], [1, 27], [-11, 82], [6, 32], [7, -9], [9, 15], [-13, 13], [2, 28], [-5, 22], [9, 12], [-16, 62]], [[3621, 5286], [5, 45], [10, 14], [-4, 41], [13, 10], [-5, 28], [24, -10], [31, 2], [50, 13], [10, -1], [-4, -57], [-14, -80], [-5, -17], [-22, 1], [-6, 11], [-31, 18], [-11, -37], [-14, -8], [-20, 7], [-7, 20]], [[4118, 8341], [17, 15], [15, -7], [-10, 75], [-11, 33], [31, -27], [9, -17], [13, -4], [21, -29], [19, 19], [-17, 60], [8, 27], [11, -11], [-1, -45], [5, -43], [-8, -31], [11, -23], [13, -42], [-30, -24]], [[6814, 5427], [-14, 10], [-41, 84], [-27, 60], [-116, 243]], [[6616, 5824], [24, 10], [19, 0], [17, 11]], [[6298, 5218], [8, 11], [-4, 36], [6, 45], [9, 14], [21, -29], [21, 27], [9, 34], [12, 8], [34, 74], [5, -13], [13, 8], [7, -49], [9, -21], [-8, -25], [12, 3], [-16, -35], [-8, -32], [-36, 7], [-9, -28], [-13, -15], [-7, 17], [-36, -33], [-8, 5], [-14, -21], [-7, 12]], [[6943, 4513], [12, 10], [-5, 59], [18, 37], [1, -15], [16, -22], [12, 2], [14, -25], [1, 31], [18, 14], [19, -21], [1, -19], [11, -35], [-4, -23], [-26, -14], [-15, 1], [-18, -46], [-10, 17], [-30, 9], [-15, 40]], [[6222, 5715], [80, 157], [37, 30], [22, 1], [34, -9], [69, -93], [-7, -11], [-9, -43], [-10, -7], [-9, -57], [8, -30], [-14, -3], [-2, -15], [-24, -35], [-31, -20], [5, -46], [-22, -19], [-23, 62], [-32, 51], [-19, -2], [-5, 18], [-13, 4], [-21, 58], [-14, 9]], [[9054, 2615], [109, 52]], [[9186, 2387], [-74, -48], [-30, -47], [2, -18], [-12, -42], [-17, -9], [-6, 9], [-6, 43], [1, 49], [-5, 12]], [[3533, 6027], [10, 47], [-7, 30], [1, 33], [6, 18], [14, -18], [-7, -19], [10, -28], [10, 14], [17, -22], [15, -1], [7, -29], [10, 15], [30, 19], [18, -16], [-4, -22], [-31, 18], [-7, -31], [-20, -10], [-8, -38], [-10, -10], [-21, 30], [-32, 14], [-1, 6]], [[7139, 3876], [-99, 80], [-5, 49], [23, 13], [22, -7], [19, 5], [45, 20], [20, 2], [14, -16], [21, -8], [13, -16], [3, -28], [-15, -19], [-10, -55], [-11, -27], [-19, -18]], [[7561, 3322], [5, 47], [16, 42], [10, -9], [12, -26], [10, 36], [20, 39], [36, -64], [10, 1], [-13, -41], [8, -8], [11, -44], [10, -9], [-25, -65], [-5, -20], [-17, 13], [-19, 6], [-14, 32], [-36, 32], [-15, 8], [-4, 30]], [[1784, 8338], [15, -4], [23, 10], [7, 22], [36, 10], [10, 9], [23, -124], [-6, -8], [-22, -1], [5, -21], [-9, 5], [-14, -12], [0, 20], [-25, -28], [-8, -31], [-26, 63], [-9, 90]], [[5343, 5948], [10, 29], [24, 43], [19, 6], [14, 34], [4, -30], [7, -9], [-13, -20], [29, -56], [-23, -29], [4, -21], [-25, -12], [-13, 47], [-13, 1], [-5, 24], [-22, -29], [3, 22]], [[10, 5796], [3, 26], [10, -6], [6, 20], [-2, 21], [6, 26], [21, -39], [12, -4], [6, 12], [12, -12], [-5, -12], [-15, 5], [-1, -32], [-7, 2], [13, -46], [-20, 17], [1, -34], [8, -32], [-9, 0], [0, -35], [-9, 9], [-15, -11], [-1, 50], [-5, 50], [-14, -2], [5, 27]], [[5805, 6601], [8, 32], [18, 25], [16, 33], [18, 14], [12, 26], [6, -3], [2, -28], [23, -31], [21, -10], [4, 11], [11, -11], [16, -55], [-31, -39], [-19, -47], [-28, 14], [-28, -10], [-18, -33], [-7, -1], [-12, 29]], [[9302, 3087], [62, 30], [26, 4], [26, 20], [55, -8], [-24, -27], [3, -10], [-14, -19], [-29, -19], [-3, -13], [16, -105]], [[9337, 2898], [-16, 35], [-7, 25], [-26, 19], [-11, 23], [13, -8], [46, 46], [-26, 24], [-8, 25]], [[6667, 7309], [-3, -48], [-8, -62], [10, -52], [34, -35], [3, 3]], [[6841, 7309], [16, -40], [-23, -86]], [[2278, 5891], [201, 42], [30, -270], [-14, -2], [8, -81]], [[7828, 1738], [11, 21], [20, -24], [24, 24], [-2, 21], [6, 21], [29, 31], [21, -7], [21, -19], [7, -24], [-42, -109], [1, -18], [-8, -7], [-18, 20], [-16, 0], [-14, 34], [-16, -13], [-20, -1], [-7, 17], [3, 33]], [[4875, 7190], [-15, -27], [-12, 6], [12, 47], [-3, 26], [48, 65], [4, 19], [17, -13], [22, 22], [7, 13], [12, -25], [-7, -16], [-28, -24], [2, -30], [-21, 8], [-22, -42]], [[6710, 7986], [17, 36], [23, 74], [22, -19], [17, 17], [25, -21], [1, -29]], [[6811, 7676], [3, 11], [-10, 57], [-9, 23], [9, 25], [-7, 13], [-50, -13], [-25, 2], [-25, 41]], [[2235, 4789], [-103, 9], [-154, 28], [-53, -1], [4, 17], [5, 62], [10, 68], [-1, 22], [5, 56], [1, 44]], [[9864, 54], [10, 24], [3, 32], [17, 1], [4, 49], [19, 0], [-3, 20], [11, 39], [-24, 30], [5, 24], [12, 13], [24, -75], [1, -87], [-12, -56], [-11, -27], [-20, -26], [-30, -15], [-7, 9], [1, 45]], [[5068, 5644], [13, 14], [-16, 26], [31, 35], [3, 22], [58, 8], [24, -13], [-3, -30], [-8, -22], [10, -3], [-8, -25], [8, -14], [-10, -27], [-10, 6], [-21, -19], [-14, 0], [-21, 15], [-27, 8], [-9, 19]], [[7031, 7303], [0, -15], [-43, -59], [-22, -46], [-14, -45], [-8, -58], [4, -27], [12, -4], [13, -64]], [[6973, 6985], [-16, -21]], [[4342, 6315], [286, 364], [19, -74], [61, -200], [16, -199], [6, -56], [14, -65], [44, -14], [-7, -21], [-185, -170], [-20, 66], [-8, 19], [-9, 43], [-29, -5], [-108, -22], [-24, 97], [-52, 216], [-4, 21]], [[6907, 8618], [15, 23], [-11, 52], [10, 38], [10, 22], [7, 46], [15, 53], [32, -23], [81, -85], [-46, -35], [-2, -16], [-11, 7], [4, -23], [-26, 25], [-3, -136], [0, -103], [-40, 38], [-5, 20], [-29, 40], [-6, 46], [5, 11]], [[1127, 6305], [-2, 147], [14, -20], [46, -166], [-1, -40], [-18, 9], [-20, 27], [-31, 26], [12, 17]], [[4327, 4830], [8, 49], [-3, 30], [20, 7], [1, 37], [-7, 6], [10, 58], [23, -21], [2, -8], [32, -18], [-8, -44], [-1, -26], [10, -57], [-27, 1], [-3, -63], [11, -33], [-51, 1], [-12, 24], [-5, 57]], [[6525, 8994], [-3, -10], [5, -50], [-27, -77], [-9, -4], [10, -26], [13, -12], [-6, -16], [2, -32], [16, -28], [-2, -18], [-48, 30], [-101, -35], [-9, 124]], [[6366, 8840], [-6, 88], [54, 67], [10, 3], [101, -4]], [[9131, 2933], [-4, 11], [18, 26], [54, 67], [78, 55], [25, -5]], [[8516, 2091], [0, -13], [-39, -96]], [[8477, 1982], [-22, -20], [-4, 22], [19, 22], [1, 16], [14, 24], [6, -11]], [[6432, 8624], [22, 25], [15, 39], [11, 6], [10, -32], [17, 9], [6, 15], [13, -2], [18, 12], [26, -71], [-9, -35], [-21, -36], [-13, -59], [-16, -6], [-9, -22], [-4, 27], [-5, -31], [-15, -6], [-19, 20], [19, 43], [-4, 22], [-27, 48], [-8, 1], [-7, 33]], [[6568, 2651], [14, -4], [62, -78], [28, -32], [1, 14], [42, -6], [33, -23], [12, -34], [14, -78], [5, -12], [-10, -15], [-56, -12], [-8, 14], [-21, 58], [-14, 69], [-35, -13], [-30, -40], [-35, -10], [0, -31], [-21, -3], [-8, -18], [0, -52], [-15, -3]], [[8114, 1833], [-15, -1], [-23, -19], [-27, 7], [-35, -14], [-13, 46], [2, 20], [23, 76], [25, -22], [32, 2]], [[7750, 5582], [8, -43], [16, -19], [10, 1], [2, -36], [-14, -43], [-12, -19], [-7, -32], [-15, 4], [-7, 47], [-42, 10], [-16, -29], [-3, -20], [-23, -5], [-14, 67], [-18, 18], [2, 45], [14, 65], [15, 12], [10, -19], [25, 4], [11, -11], [13, 30], [14, 0]], [[0, 6176], [49, -1], [2, -39], [17, -67], [2, -54], [-9, -3], [-10, 25], [4, 15], [-8, 16], [6, 11], [-23, 13], [-26, 49], [-4, 35]], [[7379, 2568], [29, 17], [17, 22], [46, 81], [22, 61], [-4, -52], [37, -58], [22, -46], [19, -52], [5, -50], [-5, -15], [-43, 14], [-12, -14], [-21, 30], [-19, 16], [-19, -1], [-12, -14], [-11, 12], [3, -31], [-8, -22], [-25, 48], [-21, 54]], [[6044, 6241], [0, 2]], [[6044, 6243], [12, 17]], [[6056, 6260], [2, 4]], [[6058, 6264], [178, 262], [17, -4]], [[6241, 6179], [-26, 1]], [[6616, 5824], [-81, 164]], [[4477, 7911], [-74, 7], [1, 47], [21, -2], [1, 37], [-21, -1], [11, 432], [0, 28], [41, 26], [202, -8], [6, -135], [7, -66], [-6, -206], [24, -43], [5, 8]], [[7161, 2631], [2, -14], [-6, -47], [3, -40], [-11, -64], [9, -27], [15, -3], [6, -17], [-12, -25], [2, -17], [17, -25], [3, -37], [-20, -31], [25, -54], [18, -108], [-10, -7], [-21, 13], [-5, 11], [-17, 74], [-17, 40], [-23, -5], [-1, -33]], [[7118, 2215], [-11, 13], [-5, 26], [-39, 39], [-6, 19]], [[7057, 2312], [-20, 67]], [[7000, 2498], [-18, 147], [35, 336], [65, 67], [57, -360], [13, -24]], [[6126, 7347], [-18, -10], [-22, -2], [-8, 24], [5, 31], [-6, 13], [1, 28], [16, 2], [11, -11], [4, 19], [29, 10]], [[7875, 4770], [-3, -38], [12, -55], [-9, -28], [-23, -14], [-24, 44], [-26, 3], [-49, -35], [6, 57], [-15, 18], [0, 18], [14, 43], [14, 8], [8, 18], [19, -6], [5, -28], [12, 42]], [[3361, 6094], [-106, -227], [-11, -18], [-9, -34], [3, -42], [-2, -69], [6, -24], [-6, -16], [7, -19], [-14, -31], [-5, -45], [7, -22], [-6, -39], [-11, -35], [-26, 1], [-12, -13], [-37, 21], [-48, -4], [-4, 22], [-10, -8], [-21, 29], [-12, 6], [-16, 41], [-16, 1], [-5, 14], [-34, -3], [-42, -41], [-35, -11], [-24, 2], [-19, 202], [101, 23], [0, 46], [-8, 0], [2, 24], [-5, 36], [10, -11], [10, 20], [18, -7], [15, 21], [2, 34], [9, 14], [25, 13], [153, 88], [11, -12], [19, 18]], [[3882, 5282], [17, -21], [15, 9], [-2, 28], [8, 4], [5, -62], [70, -50], [14, 7], [7, -64], [6, 1], [4, -26], [-12, -7], [3, -28], [9, 4], [-2, -77], [5, -46], [10, -22], [-3, -59], [-16, -82], [4, -25], [-204, 2], [-105, 9], [73, 180], [24, 83]], [[8477, 1982], [-37, -68], [-30, -28], [-38, -16], [-5, 40], [11, 25], [-23, 11], [13, 46], [10, -7], [-7, -23], [12, -12], [10, 3], [21, 31], [26, 96], [30, 37]], [[7926, 3288], [6, 11], [20, 72], [2, 48], [35, 4], [-7, -21], [8, -1], [-12, -47], [7, 8], [17, -20], [-1, -35], [-9, -1], [0, -20], [-22, 9], [-22, -12], [-22, 5]], [[7118, 2215], [2, -45], [8, -39], [-12, -61], [-25, 66], [-20, 17], [-17, 38], [-15, 5], [-1, 13], [11, 24], [2, 32], [-4, 45], [10, 2]], [[6319, 7916], [-22, 18], [6, 3], [4, 40], [-26, 41], [8, 42], [12, 32], [54, -54], [50, 168], [29, 33], [14, 47], [6, 46], [12, 14], [17, -12], [16, -55], [22, -31], [14, -96], [-18, -182], [1, -4]], [[6044, 6243], [12, 17]], [[6058, 6264], [-14, 19], [6, 31], [-8, 10], [-6, -18], [-21, -26], [3, -31], [-44, 162], [-18, 95], [174, 92]], [[8274, 911], [9, 19], [6, -11], [17, 7], [0, 18], [17, -1], [8, -15], [23, 4], [9, -28], [-27, -22], [-4, -19], [9, -26], [-23, -16], [-10, 20], [-7, -5], [-20, 44], [0, 24], [-7, 7]], [[695, 8390], [17, 94], [14, 44], [11, -14], [-7, -45], [14, -8], [19, 19], [3, 14], [26, -5], [2, -8], [-5, -64], [4, -19], [1, -47], [-37, 15], [-12, -26], [-39, 35], [-11, 15]], [[7953, 5078], [-10, -12], [-2, -48], [4, -50], [-25, -9], [10, 60], [-2, 13], [-48, -44], [3, 14], [-20, 13], [7, 22], [-6, 22], [3, 29], [21, 15], [25, 34]], [[7171, 6112], [58, 18], [13, -31], [21, 3], [11, -13], [51, -7], [-10, -24], [-22, -15], [-8, -20], [5, -35], [-7, -31], [-33, -16], [-8, 15], [-17, -5], [-18, 47], [-15, 10], [10, 40], [-29, 30], [-2, 34]], [[6973, 6985], [41, -15], [-17, -24], [0, -47], [10, -20], [8, -47], [-8, -36], [9, -16]], [[7004, 6764], [-15, 22], [-31, -3]], [[6008, 4006], [-62, -183], [-13, 7], [-9, 51], [5, 79], [15, 3], [4, 11], [19, -6], [2, 27]], [[3738, 8337], [12, 24], [19, 1], [5, 19], [7, -25], [7, 45], [57, -93], [-45, -24], [44, -71], [-27, 16], [-5, 22], [-16, 19], [-6, 21], [-10, -20], [10, -35], [3, -44], [-6, -3], [-1, -45], [-25, 3], [3, 33], [-6, 33], [-16, 21], [-6, 41], [2, 62]], [[4988, 6465], [17, 16], [-12, 10], [9, 22], [-1, 45], [-7, 3], [-5, 28], [20, -12], [19, 13], [22, -16], [2, 25], [22, 9], [14, -7], [-12, -36], [1, -34], [14, -27], [-13, -43], [7, -6], [-13, -23], [-13, -42], [-9, 8], [-34, -8], [-29, -2], [16, 44], [-29, 28], [14, 5]], [[6579, 9114], [-3, -13], [-51, -107]], [[6366, 8840], [-13, 12], [-30, 5], [-34, 13], [-15, -11], [-13, -37], [-2, -39], [-6, -36], [-11, -32], [-20, -38], [-17, 147], [-32, 262], [28, 36], [35, 17], [28, 8], [122, -56], [-12, 324], [11, 22]], [[8015, 1269], [5, 4], [-4, 37], [24, 7], [-2, 7], [26, 9], [0, 44], [25, -3], [-11, -22], [7, -9], [-4, -21], [3, -36], [7, -7], [13, 11], [11, 25], [5, -13], [-30, -33], [-5, -14], [6, -17], [19, 30], [-13, -36], [-11, 17], [-28, -14], [-15, 11], [4, 20], [-20, -5], [-11, -28], [-1, 36]]]}